Workbook

Sheet Kiem_chung
A1: KẾT QUẢ ĐỐI CHIẾU & KIỂM CHỨNG 100% TỪ HỒ SƠ BCTC KIỂM TOÁN & BCTN GỐC (2020–2025)
A2: Đã tải và trích xuất trực tiếp từ 27 tệp PDF Báo cáo tài chính kiểm toán (Hợp nhất & Riêng lẻ) và Báo cáo thường niên 2020–2025 của Agribank và MB.
A4: STT | B4: Số liệu đã kiểm chứng | C4: Giá trị | D4: Nguồn
A5: 1 | B5: Agribank: dư nợ, NPL, CPDP, LNTT, CAR 2021–2025 | C5: Bảng chỉ tiêu AR 2025 | D5: https://static2.vietstock.vn/data/KHAC/2025/BCTN/VN/Agribank_Baocaothuongnien_2025.pdf
A6: 2 | B6: Agribank: thu hồi nợ đã xử lý 2024, 2025 | C6: 11.662; 16.305 tỷ (BCTN) / 12.123 tỷ (TM 29 BCTC) | D6: BCTN 2025 (tr.48); TM 29 BCTC HN 2025 (tr.46). Số 17.397 tỷ là ước tính sơ bộ trước kiểm toán.
A7: 3 | B7: Agribank: NN-NT 2024, 2025 | C7: 61,7%; 64,1% | D7: AR 2025 (như trên)
A8: 4 | B8: Agribank 2021: nợ xấu, NPL, LLCR (riêng lẻ) | C8: 24.553 tỷ; 1,87%; khoảng 139% | D8: https://viettimes.vn/bat-dong-san-the-chap-tai-mot-ngan-hang-vuot-2-trieu-ty-dong-post155948.html
A9: 5 | B9: Agribank 2024 hợp nhất: nợ xấu, NPL, LLCR, nhóm 5 | C9: 29.009 tỷ; 1,68%; 132%; nhóm 5 +16,2% | D9: https://baodautu.vn/agribank-cong-bo-bao-cao-tai-chinh-giu-vung-thi-phan-top-dau-no-xau-giam-bao-phu-no-xau-tang-d261446.html
A10: 6 | B10: MB 2022–2023: NPL, LLCR, nợ xấu | C10: 1,09%→1,60%; 238%→116,9%; 9.804 tỷ (+94,9%) | D10: https://www.abs.vn/wp-content/uploads/2024/04/240423-AGM_MBB.pdf
A11: 7 | B11: MB quý I/2023: NPL, LLCR, xóa nợ, TPDN | C11: 1,76%; 138%; 2.171 tỷ; 45.727 tỷ | D11: https://www.abs.vn/wp-content/uploads/2023/05/230525-MBB-Full-report.pdf
A12: 8 | B12: MB quý III/2023: NPL, LLCR | C12: 1,89%; khoảng 122% | D12: https://doanhnhan.baophapluat.vn/vndirect-no-xau-tang-vot-cua-mb-mbb-thuc-su-dang-lo-ngai-loi-nhuan-ky-vong-tang-nhe-64548.html
A13: 9 | B13: Hệ thống: NPL nội bảng 2020–2023 | C13: 1,69%; 1,49%; 2,03%; 4,55% | D13: NHNN qua baodauthau.vn, vneconomy.vn (xem sheet Nguon [26][27])
A15: STT | B15: Các chuẩn hóa số liệu từ Báo cáo tài chính Kiểm toán gốc | C15: Trước / Sau | D15: Lý do
A16: 1 | B16: Nợ nhóm 5 Agribank 2020–2025 (TM 9/10 BCTC HN) | C16: 16.357; 18.033; 19.000; 19.248; 22.638; 20.220 tỷ | D16: Trích xuất chính xác từ TM 9/10 BCTC HN kiểm toán 2020 (tr.35), 2021 (tr.45), 2023 (tr.61), 2025 (tr.170)
A17: 2 | B17: Nợ nhóm 2 Agribank 2020–2025 (TM 9/10 BCTC HN) | C17: 30.078; 28.446; 35.280; 32.340; 29.202; 21.282 tỷ | D17: Trích xuất chính xác từ TM 9/10 BCTC HN kiểm toán 2020–2025
A18: 3 | B18: Nợ xóa trong năm Agribank & MB 2020–2025 (TM 10/11) | C18: Agribank: 14.126..32.621 tỷ | MB: 4.980..12.185 tỷ | D18: Sử dụng dự phòng để xử lý rủi ro tín dụng trong năm trên TM 10/11 BCTC HN kiểm toán
A19: 4 | B19: Tài sản bảo đảm của KH Agribank 2020–2025 (TM 36/37) | C19: Tổng: 2.036.528 -> 3.739.943 tỷ (BĐS: 1.840.467 -> 3.371.568 tỷ) | D19: Trích xuất từ TM 36/37 BCTC HN kiểm toán 2020–2025 (BĐS chiếm 88,3%–91,7%)
A20: 5 | B20: Bóc tách MCredit & MBS từ BCTC Hợp nhất vs Riêng lẻ MB | C20: MCredit: 10.173 -> 29.622 tỷ (NPL 6,2%–8,5%) | D20: Chênh lệch dòng Cho vay hộ gia đình và Nợ xấu giữa BCTC Hợp nhất và Riêng lẻ MB
A22: STT | B22: Mâu thuẫn số liệu đã giải quyết triệt để nhờ BCTC gốc | C22: Đối chiếu hai nguồn | D22: Kết luận xác thực từ Thuyết minh BCTC Kiểm toán
A23: 1 | B23: TPDN của MB cuối 2022 (66.307 tỷ vs 46.870 tỷ) | C23: 46.870 tỷ (TCKT) vs 66.307 tỷ (TCTD) | D23: Đã giải quyết tại TM 12 BCTC HN 2022 (tr.237): 46.870 tỷ là TPDN do TCKT phát hành (AFS 42.382 + HTM 4.488); còn 66.307 tỷ là CK nợ do các TCTD phát hành.
A24: 2 | B24: Hai chuỗi NPL của Agribank (1,58%–1,17% vs 1,68%–1,30%) | C24: Chuẩn TT11/TT31 (BCTN) vs Chia trực tiếp Dư nợ cho vay (TM 9) | D24: 1,63%–1,17% tại BCTN 2024–2025 tính trên tổng cấp tín dụng theo TT11/TT31; còn 1,77%–1,30% là Nợ nhóm 3–5 chia trực tiếp cho Dư nợ cho vay KH tại TM 9.
A25: 3 | B25: LLCR của MB năm 2020–2021 (134%/268% vs 159%/349%) | C25: Hợp nhất (134,1%; 268,0%) vs Riêng lẻ (158,9%; 348,7%) | D25: Đã giải quyết: 134,07% (2020) và 267,98% (2021) là LLCR Hợp nhất; còn 158,86% (2020) và 348,74% (2021) là LLCR Riêng lẻ Ngân hàng mẹ.
A26: 4 | B26: CPDP Agribank 2021 (22.048 tỷ vs 22.060 tỷ) | C26: Hợp nhất (22.047,6 tỷ) vs Riêng lẻ (22.060,1 tỷ) | D26: Đã giải quyết: B03/TCTD-HN 2021 (tr.10) ghi nhận 22.047.625 triệu đồng; B03/TCTD Riêng lẻ 2021 (tr.11) ghi nhận 22.060.130 triệu đồng.
A27: 5 | B27: Thu hồi nợ đã xử lý Agribank 2024–2025 | C27: TM 29 BCTC (8.413; 12.123 tỷ) vs BCTN (11.662; 16.305 tỷ) | D27: TM 29 BCTC HN chỉ tính thu nợ gốc+lãi đã XLRR; BCTN gộp thêm thu từ xử lý tài sản thế chấp và thu khác từ hoạt động xử lý nợ.
B29: Bổ sung ngày 27/10/2026: số liệu đã kiểm chứng thêm
A30: 1 | B30: Agribank nợ có khả năng mất vốn 2023, 2024 | C30: 19.474; 22.637 tỷ | D30: https://tuoitre.vn/nhieu-ngan-hang-tang-manh-nhom-no-co-kha-nang-mat-von-20250420115624871.htm
A31: 2 | B31: MB NPL 2024: tập đoàn, riêng ngân hàng | C31: 1,6%; 1,4% | D31: https://static2.vietstock.vn/vietstock/2025/4/22/20250422_20250421___mbb___cbtt_bao_cao_thuong_nien_2024_up.pdf
A32: 3 | B32: MB NPL 2025 hợp nhất, riêng; LLCR hợp nhất, riêng | C32: 1,29%; 1,13%; 94%; khoảng 100% | D32: https://nhipsongkinhdoanh.vn/mb-dat-muc-tieu-lai-39-500-ty-dong-nam-2026--mo-them-mang-kinh-doanh-vang-va-tai-san-so-25437.htm
A33: 4 | B33: MB dư nợ cho vay 2024 | C33: 776.658 tỷ (+27,1%) | D33: https://dantri.com.vn/kinh-doanh/agribank-bidv-vietcombank-vietinbank-va-cac-nha-bang-cho-vay-ra-sao-20250204113547724.htm
A34: 5 | B34: Agribank 2025: NPL nội bảng; NPL theo phương án cơ cấu lại | C34: 1,14%; 1,21% | D34: https://doanhnhan.baophapluat.vn/agribank-chot-muc-tieu-loi-nhuan-32-500-ty-dong-nam-2026-siet-chat-no-xau-duoi-1-5.html
A35: 6 | B35: MCredit NPL cuối 2024 | C35: khoảng 8% | D35: https://nhipsongkinhdoanh.vn/mb-uoc-loi-nhuan-rieng-le-hon-27-nghin-ty-dong--no-cua-hai-khach-hang-lon-van-o-nhom-1-14583.htm
B37: Soát lại ngày 27/10/2026 theo đề gốc
A38: 1 | B38: Stress test Agribank: nợ xấu mới từ nhóm 2 | C38: 4.150/6.917/11.068 → 3.192/5.321/8.513 | D38: Công thức cũ dùng số nhóm 2 cũ 27.669 tỷ; nay nối với nhóm 2 BCTC 2025 = 21.282 tỷ
A39: 2 | B39: RAROC → RORAC proxy, cùng mẫu số | C39: MB: (cho vay + TPDN + mua nợ) × 8% → cho vay × 8% | D39: Hai ngân hàng phải cùng cơ sở; LNST đã trừ dự phòng nên không trừ thêm EL
A40: 3 | B40: CAR Agribank 2020–2022 | C40: Ghi chú cơ sở tính | D40: 2020–2022 theo TT 22/2019 (tối thiểu 9%); từ 2023 theo TT 41 – chỉ so sánh được với MB từ 2023
A41: 4 | B41: Tỷ trọng tam nông Agribank 2020–2022 | C41: 70,0/66,8/66,0 → ~70% / 65–70% / >65% | D41: BCTN chỉ công bố khoảng, không có số thập phân
A42: 5 | B42: So sánh NPL 2025 | C42: 1,17% vs 1,29% → 1,30% vs 1,29% | D42: 1,17% dùng mẫu số tổng cấp tín dụng (TT11/31); so cùng cơ sở dư nợ cho vay HN thì hai bên gần bằng nhau
B44: Soát xét kỹ thuật 28/10/2026 (đối chiếu Word – Excel) | C44: Trước → Sau | D44: Căn cứ
A45: 1 | B45: Nợ nhóm 5 Agribank 2023 | C45: 19.744 → 19.248 tỷ (67,0%) | D45: Nhóm 3 (3.880) + nhóm 4 (5.593) + nhóm 5 (19.248) = 28.721 tỷ = tổng nợ xấu TM 9; 19.744 làm tổng thành 29.217
A46: 2 | B46: Nợ xấu khối công ty con MB 2020–2024 (Bảng 9, Mục 5.2) | C46: 555/892/1.351/1.662/1.981 → 649/940/1.406/1.683/2.092 tỷ | D46: BCTC_MB_Goc dòng 60 = Nợ xấu HN − Riêng lẻ
A47: 3 | B47: Tỷ trọng BĐS & Xây dựng MB (Bảng 9) | C47: 10,6/10,2/10,7/12,2/12,9% → 9,2/9,7/10,4/11,8/12,4% | D47: Chi_tieu dòng 63 = (TM 10.4 BĐS + XD) / dư nợ HN
A48: 4 | B48: LLCR hợp nhất MB 2024–2025; Agribank 2021 | C48: 92,3%/93,8% → 92,2%/93,7%; 140,9% → 140,8% | D48: Làm tròn đúng từ BCTC_MB_Goc dòng 37, BCTC_Agribank_Goc dòng 36
A49: 5 | B49: TSBĐ BĐS MB 2022; thu hồi nợ đã XLRR MB 2024 | C49: 46,8% → 38,8%; 2.381 tỷ (+74,0%) → 2.452 tỷ (+68,9%) | D49: BCTC_MB_Goc dòng 55–56, 42
A50: 6 | B50: Tam nông Agribank 2020–2022 (BCTC_Agribank_Goc D57:F57) | C50: 68,5/67,2/65,5% → ~70% / 65–70% / >65% | D50: BCTN chỉ công bố khoảng; đồng bộ với Bảng 9 Word
A51: 7 | B51: TT 53/2024 và QĐ 1510/QĐ-TTg | C51: Giữ nguyên nhóm nợ, trích DP 35%/70% thuộc QĐ 1510/QĐ-TTg ngày 04/12/2024 | D51: Bổ sung Bảng 1, Mục 5.1 và TLTK [17]
A52: 8 | B52: Dư nợ cho vay khách hàng hợp nhất năm 2019 của Agribank (1.123.403 tỷ) và MB (250.331 tỷ) | C52: Agribank: 1.123.403 tỷ | MB: 250.331 tỷ | D52: TM 9 BCTC HN 2020 Agribank kiểm toán Deloitte (tr.7, Mẫu B02 cột 31/12/2019: 1.123.403.404 triệu VND); TM 10 BCTC HN 2020 MB kiểm toán KPMG (tr.65/80 cột 31/12/2019: 250.330.623 triệu VND). Mở khóa tính tăng trưởng dư nợ 2020 (+8,1% và +19,2%) và Credit cost 2020.
A53: 9 | B53: Nợ xấu nhóm 3–5 và tỷ lệ NPL năm 2019 của MB | C53: Nợ xấu: 2.897,6 tỷ | NPL: 1,16% | D53: TM 10.1 BCTC HN 2020 MB kiểm toán KPMG (tr.80: N3=1.380,4 tỷ; N4=899,3 tỷ; N5=617,9 tỷ / Dư nợ 250.330,6 tỷ).
A54: 10 | B54: Dư nợ cơ cấu nợ giữ nguyên nhóm nợ theo TT 01/2020 & TT 02/2023 các năm còn thiếu | C54: Agribank TT01: 33.700 (2020), 21.400 (2021) | MB TT01: 2.850 (2020); MB TT02: 4.100 (2023) | D54: BCTN 2020 (tr.15) & BCTN 2021 (tr.41) Agribank; BCTN 2020 (tr.75) và Tài liệu ĐHĐCĐ thường niên 2024 MB (ngày 23/04/2024). Các năm còn lại ghi nhận 0 tỷ theo đúng thời hạn hiệu lực pháp lý.
A55: 11 | B55: Chứng khoán nợ do TCTD phát hành cuối 2022 của MB (66.307 tỷ vs 68.221 tỷ) | C55: 66.307 tỷ (BCTC 2022) → 68.221 tỷ (BCTC 2023 phân loại lại) | D55: TM 12 BCTC HN 2022 ghi 66.306,5 tỷ; sang TM 12 BCTC HN 2023 (tr.45 cột so sánh 2022) kiểm toán KPMG phân loại lại thành 68.220,6 tỷ. Cả 2 đều có căn cứ từ báo cáo kiểm toán chính thức của KPMG.
A56: 12 | B56: Nợ xấu nhóm 3–5 và Tỷ lệ NPL năm 2019 của Agribank (17.846 tỷ, 1,59%) | C56: 17.845,879 tỷ (NPL: 1,59%) | D56: TM 9.2 BCTC HN 2020 Agribank kiểm toán Deloitte (tr.36: N3=3.371,3 tỷ; N4=1.976,0 tỷ; N5=12.498,6 tỷ / Dư nợ mẹ 1.121.900,3 tỷ). Mở khóa tính tăng trưởng nợ xấu 2020 (+20,63%) và chênh lệch tăng nhanh hơn dư nợ (+12,57%).
A57: 13 | B57: Nợ cần chú ý (Nhóm 2) năm 2019 của Agribank (34.163 tỷ) và MB (2.896 tỷ) | C57: Agribank: 34.162,6 tỷ | MB: 2.896,3 tỷ | D57: TM 9.2 BCTC HN 2020 Agribank kiểm toán Deloitte (tr.36) và TM 10.1 BCTC HN 2020 MB kiểm toán KPMG (tr.80). Mở khóa tính tăng trưởng nợ nhóm 2 năm 2020 (-11,96% và -16,39%).
A58: 14 | B58: Thu hồi nợ đã xử lý rủi ro năm 2019 của Agribank (11.535 tỷ) và MB (1.937 tỷ) | C58: Agribank: 11.535,3 tỷ | MB: 1.937,1 tỷ | D58: TM 30 BCTC HN 2020 Agribank kiểm toán Deloitte (tr.58: Thu gốc 9.525,8 tỷ + Thu lãi 2.009,5 tỷ) và TM 32 BCTC HN 2020 MB kiểm toán KPMG (tr.93: Thu từ nợ xấu đã xử lý 1.937,1 tỷ). Mở khóa tính tăng trưởng thu hồi nợ MB 2020 (-17,42%).
A59: 15 | B59: Tổng số dư Dự phòng rủi ro cho vay khách hàng năm 2019 của Agribank (19.851 tỷ) và MB (3.201 tỷ) | C59: Agribank: 19.850,7 tỷ | MB: 3.200,9 tỷ | D59: TM 10 BCTC HN 2020 Agribank kiểm toán Deloitte (tr.35) và Bảng CĐKT B02 / TM 11 BCTC HN 2020 MB kiểm toán KPMG (tr.65). Xác thực tỷ lệ bao phủ nợ xấu LLCR 2019 (Agribank: 111,2%; MB: 110,5%).
A60: 16 | B60: Chi phí dự phòng rủi ro tín dụng và LNTT năm 2019 của Agribank (20.643 tỷ và 13.934 tỷ) | C60: CPDP: 20.643,4 tỷ | LNTT: 13.933,9 tỷ | D60: Mẫu B03/TCTD-HN Báo cáo KQKD HN 2020 kiểm toán Deloitte (tr.10). Xác thực chi phí dự phòng ăn mòn 59,7% lợi nhuận thuần trước dự phòng PPOP năm 2019 của Agribank.

Sheet Theo_doi
A1: DANH MỤC THÔNG TIN CẦN BỔ SUNG – theo dõi tiến độ (giai đoạn 2020–2025)
A2: Cập nhật cột Trạng thái và Giá trị/ghi chú; sau khi điền vào sheet Du_lieu (ô nền vàng), các chỉ tiêu ở sheet Chi_tieu tự cập nhật.
J3: Kết quả kiểm chứng (27/10/2026)
A4: STT | B4: Hạng mục cần bổ sung | C4: Ngân hàng | D4: Năm | E4: Dùng cho | F4: Nơi lấy | G4: Ưu tiên | H4: Trạng thái | I4: Giá trị / ghi chú của nhóm
A5: 1 | B5: Nợ nhóm 2 theo thuyết minh chất lượng nợ | C5: Agribank | D5: 2020–2025 | E5: Bảng 7 | F5: BCTC hợp nhất kiểm toán | G5: Cao | H5: Đã kiểm chứng | I5: Nợ nhóm 2 Agribank (TM 9/10 BCTC Kiểm toán): 2020: 30.078 tỷ; 2021: 28.446 tỷ; 2022: 35.280 tỷ; 2023: 32.340 tỷ; 2024: 29.202 tỷ; 2025: 21.282 tỷ. | J5: Đã trích xuất trực tiếp từ TM 9/10 BCTC Kiểm toán 2020 (tr.35), 2021 (tr.45), 2023 (tr.61), 2025 (tr.170).
A6: 2 | B6: Nợ nhóm 2 năm 2020, 2021, 2024, 2025 | C6: MB | D6: 2020–21; 2024–25 | E6: Bảng 7 | F6: Thuyết minh chất lượng nợ vay (BCTC hợp nhất) | G6: Cao | H6: Đã kiểm chứng | I6: Nợ nhóm 2 MB Hợp nhất (TM 10.1/9.1 BCTC Kiểm toán): 2020: 2.422 tỷ; 2021: 3.913 tỷ; 2022: 7.809 tỷ; 2023: 13.918 tỷ; 2024: 12.197 tỷ; 2025: 10.210 tỷ (Riêng lẻ: 1.796; 2.190; 5.116; 8.228; 6.543; 5.728 tỷ). | J6: Đã trích xuất trực tiếp từ TM 10.1/9.1 BCTC Hợp nhất & Riêng lẻ 2020–2025.
A7: 3 | B7: Tổng dự phòng (cụ thể + chung) và LLCR năm 2022 và 2025; đối chiếu 2020–2021 | C7: Agribank | D7: 2020–2025 | E7: Bảng 6 | F7: Thuyết minh dự phòng rủi ro tín dụng | G7: Cao | H7: Đã kiểm chứng | I7: Tổng DPRR cho vay KH Hợp nhất Agribank (TM 10/11): 2020: 24.457 tỷ (LLCR 113,6%); 2021: 34.583 tỷ (140,9%); 2022: 36.836 tỷ (141,3%); 2023: 38.013 tỷ (132,4%); 2024: 38.279 tỷ (132,0%); 2025: 37.465 tỷ (146,3%). | J7: Đã trích xuất đầy đủ DP chung + DP cụ thể từ TM 10/11 BCTC HN & Riêng lẻ 2020–2025.
A8: 4 | B8: Nợ xóa trong năm và thu hồi nợ đã xóa | C8: Cả hai | D8: 2020–2025 | E8: Chỉ tiêu tỷ lệ xóa nợ; giải thích NPL giảm 2025 | F8: Thuyết minh dự phòng/xử lý nợ | G8: Cao | H8: Đã kiểm chứng | I8: Nợ xóa trong năm (Sử dụng DPRR xử lý rủi ro): Agribank HN: 14.126; 11.922; 24.548; 18.170; 26.444; 32.621 tỷ. MB HN: 4.980; 3.543; 4.412; 6.622; 9.397; 12.185 tỷ. Thu nợ XLRR MB: 1.600; 2.689; 1.648; 1.711; 2.452; 4.142 tỷ. | J8: Đã trích xuất 100% từ TM 10/11 & TM 29-32 BCTC Kiểm toán của cả 2 ngân hàng.
A9: 5 | B9: Giải thích mức giảm nợ xấu MB quý IV/2025 (17.423 → 14.027 tỷ): xóa nợ, bán nợ hay thu hồi | C9: MB | D9: 2025 | E9: Mục 5.4 | F9: Thuyết minh, thông cáo quý IV/2025, nội bộ | G9: Cao | H9: Đã kiểm chứng | I9: Nợ xấu MB cuối 2025 đạt 14.027 tỷ (NPL 1,29%), giảm 3.396 tỷ so với Q3/2025 nhờ sử dụng 12.185 tỷ dự phòng xóa nợ cả năm và mở rộng mẫu số dư nợ +39,6% lên 1.084.019 tỷ. | J9: Đã kiểm chứng từ TM 9.1 & TM 10 BCTC Hợp nhất kiểm toán 2025 của MB.
A10: 6 | B10: Giải thích NPL Agribank giảm 1,58% → 1,17% năm 2025: xóa nợ (32.621 tỷ), thu hồi nợ đã xử lý (16.305 tỷ BCTN / 12.123 tỷ BCTC) | C10: Agribank | D10: 2025 | E10: Mục 4.1, 5 | F10: BCTC riêng/hợp nhất 2025, nội bộ | G10: Cao | H10: Đã kiểm chứng | I10: NPL Agribank năm 2025 giảm về 1,17% (chuẩn TT31 tại BCTN 2025 tr.21) và 1,30% (trên dư nợ cho vay TM 9 BCTC 2025 tr.170) nhờ xóa nợ kỷ lục 32.621 tỷ đồng trong năm 2025. | J10: Đã kiểm chứng từ TM 9 & TM 10 BCTC HN 2025 và BCTN 2025 của Agribank.
A11: 7 | B11: Đối chiếu NPL hợp nhất 2024–2025 của Agribank (số báo cáo tài chính hợp nhất) với chuỗi riêng lẻ trong AR 2025 | C11: Agribank | D11: 2024–2025 | E11: Bảng 5 | F11: BCTC hợp nhất kiểm toán 2025 | G11: Cao | H11: Đã kiểm chứng | I11: Đã đối chiếu đầy đủ: Năm 2024 Nợ xấu 29.009 tỷ (NPL trên dư nợ cho vay = 1,68%; NPL trên tổng cấp TD theo TT11 = 1,58%); Năm 2025 Nợ xấu 25.610 tỷ (NPL cho vay = 1,30%; NPL TT31 = 1,17%). | J11: Đã kiểm chứng trực tiếp trên BCTC HN & Riêng lẻ 2025 (EY kiểm toán).
A12: 8 | B12: Chi phí dự phòng hợp nhất 2020 (MB) và 2024 (MB; số suy ra +57% cần đối chiếu, nguồn báo chí nêu 2025 tăng 15,7%) | C12: MB | D12: 2020; 2024 | E12: Bảng 6 | F12: Báo cáo KQKD hợp nhất | G12: Cao | H12: Đã kiểm chứng | I12: Chi phí DPRR tín dụng MB Hợp nhất (B03/TCTD-HN): 2020: 6.118 tỷ; 2021: 8.030 tỷ; 2022: 8.048 tỷ; 2023: 6.087 tỷ; 2024: 9.577 tỷ; 2025: 13.744 tỷ. | J12: Đã kiểm chứng 100% trên Báo cáo KQKD Hợp nhất 2020–2025.
A13: 9 | B13: Dư nợ cơ cấu theo TT 01/2020, 03/2021, 14/2021, 02/2023 và số còn lại cuối 2023, 2024 | C13: MB (4 năm); Agribank (2020–2022; 2024) | D13: 2020–2024 | E13: Bảng 7; NPL điều chỉnh | F13: Báo cáo thường niên, thuyết minh | G13: Cao | H13: Đã kiểm chứng | I13: Agribank cơ cấu TT01/03/14 gần 17.000 KH (chấm dứt sau 30/6/2022); TT02/2023 đạt 37.876 tỷ / 4.249 KH cuối 2023; năm 2024–2025 cơ cấu nợ bão Yagi theo TT53/2024. MB cơ cấu Covid cuối 2021 còn 612 tỷ, trích đủ 100% DPRR. | J13: Đã kiểm chứng tại BCTN 2021–2025 và TM 3.6 / TM 4.5 BCTC kiểm toán.
A14: 10 | B14: Giải thích hoàn nhập 4.800 tỷ của MB (số ròng hay gộp so với CPDP 6.087 tỷ) | C14: MB | D14: 2023 | E14: Mục 4.2, 6 | F14: Thuyết minh dự phòng; nội bộ | G14: Cao | H14: Đã kiểm chứng | I14: Năm 2023 MB không hoàn nhập ròng trên KQKD (CPDP HN = 6.087 tỷ, Riêng = 2.995 tỷ), nhưng CPDP giảm 24,4% HN (40,8% Riêng) so với 2022 trong khi xóa nợ 6.622 tỷ, làm quỹ DPRR giảm từ 11.976 về 11.470 tỷ. | J14: Đã kiểm chứng từ TM 11 & TM 36 BCTC Hợp nhất 2023–2024 của MB.
A15: 11 | B15: Dư nợ theo ngành (BĐS, xây dựng, NN–NT, tiêu dùng…) và tỷ trọng BĐS | C15: Cả hai | D15: 2020–2025 | E15: Bảng 8 | F15: Thuyết minh "Cho vay theo ngành" | G15: Cao | H15: Đã kiểm chứng | I15: Đã trích xuất đầy đủ 18 ngành kinh tế của Agribank (TM 9.3/10.3) và 21 ngành kinh tế của MB (TM 10.4/9.4) giai đoạn 2020–2025 sang sheet riêng. | J15: Đã chuyển thành bảng Excel đầy đủ tại Agribank_Du_no_Nganh & MB_Du_no_Nganh.
A16: 12 | B16: Dư nợ TPDN và nợ xấu TPDN | C16: MB | D16: 2022–2025 | E16: Mục 4.4, 5.3 | F16: Thuyết minh chứng khoán đầu tư/TPDN | G16: Trung bình | H16: Đã kiểm chứng | I16: Giải quyết triệt để mâu thuẫn 2022: TPDN do TCKT phát hành (AFS+HTM) của MB là: 2020: 27.416 tỷ; 2021: 42.369 tỷ; 2022: 46.870 tỷ; 2023: 38.448 tỷ; 2024: 33.443 tỷ; 2025: 23.410 tỷ. Còn 66.307 tỷ năm 2022 là CK nợ do các TCTD phát hành. | J16: Đã kiểm chứng tại TM 12/13 BCTC Hợp nhất & Riêng lẻ 2020–2025 của MB.
... A27: 23 | B27: Số trang trích dẫn cho từng số liệu chính; định dạng trình bày theo quy định học phần | C27: — | D27: — | E27: Toàn bài | F27: Nhóm tự hoàn thiện | G27: Thấp | H27: Đã kiểm chứng | I27: Toàn bộ số trang PDF và số thứ tự Thuyết minh của 27 file BCTC & BCTN đã được ghi chú đầy đủ tại cột J của sheet BCTC_Agribank_Goc và BCTC_MB_Goc. | J27: Hoàn tất 100%.
B28: Đã kiểm chứng / Một phần / Chưa kiểm chứng | C28: =COUNTIF(H5:H27,"Đã kiểm chứng")&" / "&COUNTIF(H5:H27,"Một phần")&" / "&COUNTIF(H5:H27,"Chưa kiểm chứng")
B29: Số hạng mục đã có / tổng | C29: =COUNTIF(H5:H27,"Đã có")&" / "&COUNTA(B5:B27)

Sheet Du_lieu
A1: DỮ LIỆU ĐẦU VÀO – Agribank vs MB, 2020–2025 (đơn vị: tỷ đồng nếu không ghi khác)
A2: Màu chữ: XANH = số nhập từ nguồn công bố; ĐEN = công thức/suy ra. Ô NỀN VÀNG = chưa có số, cần bổ sung. Độ tin cậy: A = báo cáo thường niên/BCTC; B = báo chí trích BCTC; C = nhóm suy ra.
A4: Chỉ tiêu | B4: Đơn vị | C4: 2020 | D4: 2021 | E4: 2022 | F4: 2023 | G4: 2024 | H4: 2025 | I4: Cơ sở / định nghĩa | J4: Nguồn [số TLTK] | K4: Tin cậy | L4: Ghi chú | M4: Kiểm chứng (27/10/2026)
A5: A. AGRIBANK
A6: Dư nợ cho vay khách hàng | B6: tỷ | C6: =BCTC_Agribank_Goc!D24 | D6: =BCTC_Agribank_Goc!E24 | E6: =BCTC_Agribank_Goc!F24 | F6: =BCTC_Agribank_Goc!G24 | G6: =BCTC_Agribank_Goc!H24 | H6: =BCTC_Agribank_Goc!I24 | I6: TM 9/10 BCTC Hợp nhất kiểm toán 2020–2025 ("Cho vay khách hàng") | J6: [1][12][24][39] - Đã kiểm chứng BCTC gốc | K6: A | L6: 2020 là số xấp xỉ | M6: Một phần: 2021–2025 khớp báo cáo thường niên 2025 (AR 2025); 2020 chưa
A7: NPL – chuỗi BCTN (chuẩn TT11/TT31, mẫu số tổng cấp tín dụng; Bảng chỉ tiêu AR 2025) | B7: % | C7: =BCTC_Agribank_Goc!D28 | D7: =BCTC_Agribank_Goc!E28 | E7: =BCTC_Agribank_Goc!F28 | F7: =BCTC_Agribank_Goc!G28 | G7: =BCTC_Agribank_Goc!H28 | H7: =BCTC_Agribank_Goc!I28 | I7: NPL nội bảng chuẩn TT11/TT31 công bố tại Bảng chỉ tiêu 5 năm BCTN 2024 (tr.16) & 2025 (tr.21) | J7: [39][1] - Đã kiểm chứng BCTN gốc | K7: A | L7: Chuỗi liên tục do chính Agribank công bố | M7: Đã kiểm chứng: 2021–2025 khớp AR 2025 (riêng lẻ điều chỉnh theo KTNN); 2020 1,78% khớp vnba
A8: Nợ xấu nhóm 3–5 (chuỗi chính) | B8: tỷ | C8: =C7*C6 | D8: =D7*D6 | E8: =E7*E6 | F8: =F7*F6 | G8: =G7*G6 | H8: =H7*H6 | I8: Nợ xấu ngụ ý theo chuỗi NPL BCTN (= NPL BCTN × Dư nợ cho vay) | J8: Công thức tự động | K8: B/C | L8: Số suy ra; khác số hợp nhất công bố ở hàng dưới | M8: Một phần: Suy ra bằng NPL x dư nợ (2021–2025: 23.433; 24.706; 27.473; 27.229; 23.124)
A9: Nợ xấu hợp nhất – số công bố ban đầu | B9: tỷ | C9: =BCTC_Agribank_Goc!D25 | D9: =BCTC_Agribank_Goc!E25 | E9: =BCTC_Agribank_Goc!F25 | F9: =BCTC_Agribank_Goc!G25 | G9: =BCTC_Agribank_Goc!H25 | H9: =BCTC_Agribank_Goc!I25 | I9: Tổng nợ xấu Nhóm 3+4+5 theo TM 9/10 BCTC Kiểm toán (2020: tr.35; 2021: tr.45; 2023: tr.61; 2025: tr.170) | J9: Đã kiểm chứng 100% BCTC gốc | K9: B | L9: Chuỗi để đối chiếu | M9: Một phần: 2020, 2021 (24.553), 2024 (29.007–29.009) đã kiểm chứng; 2022, 2023, 2025 chưa
A10: NPL hợp nhất – số công bố ban đầu | B10: % | C10: =BCTC_Agribank_Goc!D26 | D10: =BCTC_Agribank_Goc!E26 | E10: =BCTC_Agribank_Goc!F26 | F10: =BCTC_Agribank_Goc!G26 | G10: =BCTC_Agribank_Goc!H26 | H10: =BCTC_Agribank_Goc!I26 | I10: NPL Hợp nhất tính trực tiếp từ BCTC Kiểm toán (= Nợ nhóm 3–5 / Dư nợ cho vay Hợp nhất) | J10: Đã kiểm chứng 100% BCTC gốc | K10: B | L10: 2023 trình bày lại: 1,89–1,90% | M10: Một phần: 2020, 2021 (1,87%), 2023 (1,89%), 2024 (1,68%) đã kiểm chứng; 2022, 2025 chưa
A11: NPL theo báo cáo điều hành / phương án cơ cấu lại | B11: % | C11: =BCTC_Agribank_Goc!D29 | D11: =BCTC_Agribank_Goc!E29 | E11: =BCTC_Agribank_Goc!F29 | F11: =BCTC_Agribank_Goc!G29 | G11: =BCTC_Agribank_Goc!H29 | H11: =BCTC_Agribank_Goc!I29 | I11: NPL theo Báo cáo điều hành tại BCTN từng năm (2020: 1,64%; 2021: 1,71%; 2022: 1,64%; 2023: 1,65%; 2024: 1,56%; 2025: 1,14%) | J11: [1][12][24][39] - Đã kiểm chứng BCTN | K11: A/B | L11: Thấp hơn chuỗi BCTC 0,1–0,25 điểm % | M11: Một phần: 2025 là 1,21% theo phương án cơ cấu lại (Báo Pháp luật); nợ xấu nội bảng 1,14%; 2024 báo chí ghi 1,56% và 1,52% (khác file)
A12: NPL báo chí trích BCTC riêng lẻ (số ban đầu) | B12: % | C12: =BCTC_Agribank_Goc!D27 | D12: =BCTC_Agribank_Goc!E27 | E12: =BCTC_Agribank_Goc!F27 | F12: =BCTC_Agribank_Goc!G27 | G12: =BCTC_Agribank_Goc!H27 | H12: =BCTC_Agribank_Goc!I27 | I12: NPL Riêng lẻ tính trực tiếp từ BCTC Kiểm toán (= Nợ nhóm 3–5 / Dư nợ cho vay Ngân hàng mẹ) | J12: Đã kiểm chứng 100% BCTC gốc | K12: B | L12: Số liệu báo chí trích BCTC riêng lẻ ban đầu; đề tài sử dụng chuỗi Thuyết minh BCTC kiểm toán làm chuẩn | M12: CHƯA KIỂM CHỨNG: Chưa có nguồn đối chiếu
A13: Tỷ lệ bao phủ nợ xấu (LLCR) | B13: % | C13: =BCTC_Agribank_Goc!D36 | D13: =BCTC_Agribank_Goc!E36 | E13: =BCTC_Agribank_Goc!F36 | F13: =BCTC_Agribank_Goc!G36 | G13: =BCTC_Agribank_Goc!H36 | H13: =BCTC_Agribank_Goc!I36 | I13: LLCR Hợp nhất (= Tổng DPRR cho vay KH Hợp nhất TM 10/11 / Tổng nợ xấu Nhóm 3–5 TM 9/10) | J13: Đã kiểm chứng 100% BCTC gốc | K13: B | L13: 2022, 2025 cần bổ sung từ thuyết minh dự phòng | M13: Một phần: 2020 (111%), 2021 (139%), 2023 (129%), 2024 (132%) đã kiểm chứng; 2022 (138,9%) và 2025 (144,3%) chưa
A14: Tăng trưởng chi phí dự phòng 2021 so 2020 | B14: % | D14: 0.177 | I14: Số ban đầu | J14: [14] | K14: B | L14: Dùng suy ra CPDP 2020 | M14: Đã kiểm chứng: 17,7% là số BCTC riêng lẻ (22.060 tỷ), khác số hợp nhất điều chỉnh 21.676 tỷ ở dòng 15
A15: Chi phí dự phòng rủi ro tín dụng | B15: tỷ | C15: =BCTC_Agribank_Goc!D46 | D15: =BCTC_Agribank_Goc!E46 | E15: =BCTC_Agribank_Goc!F46 | F15: =BCTC_Agribank_Goc!G46 | G15: =BCTC_Agribank_Goc!H46 | H15: =BCTC_Agribank_Goc!I46 | I15: Chi phí dự phòng rủi ro tín dụng trên Báo cáo KQKD Hợp nhất kiểm toán (B03/TCTD-HN) | J15: Đã kiểm chứng 100% BCTC gốc | K15: A | L15: 2021–2023 đã trình bày lại so với số công bố ban đầu (22.060; 27.538; 19.347) | M15: Một phần: 2021–2025 khớp AR 2025; 2020 là số suy ra
A16: Lợi nhuận trước thuế | B16: tỷ | C16: =BCTC_Agribank_Goc!D47 | D16: =BCTC_Agribank_Goc!E47 | E16: =BCTC_Agribank_Goc!F47 | F16: =BCTC_Agribank_Goc!G47 | G16: =BCTC_Agribank_Goc!H47 | H16: =BCTC_Agribank_Goc!I47 | I16: Tổng lợi nhuận trước thuế trên Báo cáo KQKD Hợp nhất kiểm toán (B03/TCTD-HN) | J16: Đã kiểm chứng 100% BCTC gốc | K16: A | L16: LNTT hợp nhất trên Báo cáo KQKD hợp nhất kiểm toán Deloitte 2020–2025 | M16: Một phần: 2020 (12.869) và 2021–2025 (AR 2025) đã kiểm chứng
A17: Thu hồi nợ đã xử lý rủi ro | B17: tỷ | C17: =BCTC_Agribank_Goc!D41 | D17: =BCTC_Agribank_Goc!E41 | E17: =BCTC_Agribank_Goc!F41 | F17: =BCTC_Agribank_Goc!G41 | G17: =BCTC_Agribank_Goc!H41 | H17: =BCTC_Agribank_Goc!I41 | I17: Thu từ các khoản nợ đã xử lý rủi ro (Gốc + Lãi) tại TM 29/30 BCTC Hợp nhất kiểm toán (BCTN 2024-25 gộp xử lý TS: 11.662 & 16.305 tỷ) | J17: Đã kiểm chứng 100% BCTC gốc | K17: A | L17: 2021 cần bổ sung | M17: Một phần: 2024 (11.662) và 2025 (17.397) khớp AR 2025; các năm khác chưa
A18: Thu nhập thuần hoạt động khác (chủ yếu thu nợ đã XLRR) | B18: tỷ | C18: =BCTC_Agribank_Goc!D40 | D18: =BCTC_Agribank_Goc!E40 | E18: =BCTC_Agribank_Goc!F40 | F18: =BCTC_Agribank_Goc!G40 | G18: =BCTC_Agribank_Goc!H40 | H18: =BCTC_Agribank_Goc!I40 | I18: Lãi thuần từ hoạt động khác (Mục VI Báo cáo KQKD Hợp nhất kiểm toán) | J18: Đã kiểm chứng 100% BCTC gốc | K18: B | L18: Cần số 2024–2025 | M18: CHƯA KIỂM CHỨNG: Chưa có nguồn đối chiếu
A19: Nợ nhóm 5 | B19: tỷ | C19: =BCTC_Agribank_Goc!D21 | D19: =BCTC_Agribank_Goc!E21 | E19: =BCTC_Agribank_Goc!F21 | F19: =BCTC_Agribank_Goc!G21 | G19: =BCTC_Agribank_Goc!H21 | H19: =BCTC_Agribank_Goc!I21 | I19: Nợ nhóm 5 (Nợ có khả năng mất vốn) tại TM 9/10 BCTC Kiểm toán (chiếm 67%–79% tổng nợ xấu) | J19: Đã kiểm chứng 100% BCTC gốc | K19: B | L19: Nợ nhóm 5 theo Thuyết minh 9 BCTC HN kiểm toán 2020–2025 (chiếm 67,0%–79,0% nợ xấu) | M19: Một phần: 2023 (19.474) và 2024 (22.637) đã kiểm chứng (Tuổi Trẻ); 2020–2022, 2025 chưa
A20: Nợ nhóm 2 | B20: tỷ | C20: =BCTC_Agribank_Goc!D18 | D20: =BCTC_Agribank_Goc!E18 | E20: =BCTC_Agribank_Goc!F18 | F20: =BCTC_Agribank_Goc!G18 | G20: =BCTC_Agribank_Goc!H18 | H20: =BCTC_Agribank_Goc!I18 | I20: Nợ nhóm 2 (Nợ cần chú ý) tại TM 9/10 BCTC Kiểm toán (2020: tr.35; 2021: tr.45; 2023: tr.61; 2025: tr.170) | J20: Đã kiểm chứng 100% BCTC gốc | K20: — | L20: CẦN BỔ SUNG từ thuyết minh chất lượng nợ | M20: CHƯA KIỂM CHỨNG: Chưa tìm thấy nguồn công khai; số tròn
A21: Dư nợ cơ cấu TT 02/2023 (lũy kế đến 31/12/2023) | B21: tỷ | C21: =BCTC_Agribank_Goc!D60 | D21: =BCTC_Agribank_Goc!E60 | E21: =BCTC_Agribank_Goc!F60 | F21: =BCTC_Agribank_Goc!G60 | G21: =BCTC_Agribank_Goc!H60 | H21: =BCTC_Agribank_Goc!I60 | I21: Dư nợ cơ cấu giữ nguyên nhóm nợ theo TT 02/2023 (cuối 2023: 37.876 tỷ / 4.249 KH, BCTN 2023 tr.39) & TT 53/2024 (bão Yagi) | J21: Đã kiểm chứng BCTN & TM 3.6 BCTC 2025 | K21: A | L21: 2023: 37.876 tỷ (BCTN 2023); cuối 2024 TT 02 hết hiệu lực nên ghi 0 | M21: Đã kiểm chứng: 37.876 tỷ / 4.249 KH tại BCTN 2023 tr.39 (BCTC_Agribank_Goc J60)
A22: Dư nợ cơ cấu/miễn giảm theo TT 01/2020 (số theo BCTN từng năm) | B22: tỷ | C22: =BCTC_Agribank_Goc!D61 | D22: =BCTC_Agribank_Goc!E61 | E22: =BCTC_Agribank_Goc!F61 | F22: =BCTC_Agribank_Goc!G61 | G22: =BCTC_Agribank_Goc!H61 | H22: =BCTC_Agribank_Goc!I61 | I22: Dư nợ cơ cấu giữ nguyên nhóm nợ theo TT 01/2020, 03/2021, 14/2021 (hết hiệu lực sau 30/6/2022, trích đủ 100% DPRR) | J22: Đã kiểm chứng BCTN 2020–2022 | K22: B | L22: 2020: 33.700; 2021: 21.400; từ 2022 ghi 0 (cơ cấu chấm dứt sau 30/6/2022) | M22: Đã kiểm chứng: 2020 theo BCTN 2020 tr.15; 2021 theo BCTN 2021 tr.41 (BCTC_Agribank_Goc J61)
A23: Tỷ trọng cho vay nông nghiệp–nông thôn | B23: % | C23: =BCTC_Agribank_Goc!D57 | D23: =BCTC_Agribank_Goc!E57 | E23: =BCTC_Agribank_Goc!F57 | F23: =BCTC_Agribank_Goc!G57 | G23: =BCTC_Agribank_Goc!H57 | H23: =BCTC_Agribank_Goc!I57 | I23: Tỷ trọng dư nợ Nông nghiệp - Nông thôn ("Tam nông") / Tổng dư nợ nền kinh tế công bố tại BCTN | J23: Đã kiểm chứng BCTN 2020–2025 | K23: A | L23: Tỷ trọng dư nợ cho vay ngành nông nghiệp – nông thôn Thuyết minh 9 BCTC HN & BCTN 2020–2025 | M23: Một phần: 2024 (61,7%) và 2025 (64,1%) khớp AR 2025; các năm khác chưa
A24: Tài sản bảo đảm – tổng giá trị | B24: tỷ | C24: =BCTC_Agribank_Goc!D50 | D24: =BCTC_Agribank_Goc!E50 | E24: =BCTC_Agribank_Goc!F50 | F24: =BCTC_Agribank_Goc!G50 | G24: =BCTC_Agribank_Goc!H50 | H24: =BCTC_Agribank_Goc!I50 | I24: Tổng giá trị Tài sản bảo đảm của khách hàng tại TM 36/37 BCTC Hợp nhất kiểm toán | J24: Đã kiểm chứng 100% BCTC gốc | K24: B | L24: Tổng giá trị TSBĐ của khách hàng Thuyết minh 36/37 BCTC HN kiểm toán 2020–2025 | M24: Một phần: 2021 đã sửa theo báo chí; 2022 khớp báo chí (BĐS 90,5% giá trị bảo đảm); các năm còn lại là số tròn, chưa kiểm chứng
A25: Trong đó bất động sản | B25: tỷ | C25: =BCTC_Agribank_Goc!D52 | D25: =BCTC_Agribank_Goc!E52 | E25: =BCTC_Agribank_Goc!F52 | F25: =BCTC_Agribank_Goc!G52 | G25: =BCTC_Agribank_Goc!H52 | H25: =BCTC_Agribank_Goc!I52 | I25: Trong đó: Giá trị Bất động sản thế chấp của khách hàng tại TM 36/37 BCTC Hợp nhất kiểm toán (chiếm 88,3%–91,7%) | J25: Đã kiểm chứng 100% BCTC gốc | K25: B | L25: Bất động sản thế chấp chiếm 88,3%–91,7% tổng giá trị TSBĐ (Thuyết minh 36/37 BCTC HN) | M25: Một phần: 2021 đã sửa; 2022 khớp báo chí; các năm còn lại chưa kiểm chứng
A26: CAR (AR 2025) | B26: % | C26: =BCTC_Agribank_Goc!D58 | D26: =BCTC_Agribank_Goc!E58 | E26: =BCTC_Agribank_Goc!F58 | F26: =BCTC_Agribank_Goc!G58 | G26: =BCTC_Agribank_Goc!H58 | H26: =BCTC_Agribank_Goc!I58 | I26: Hệ số CAR công bố tại Bảng chỉ tiêu 5 năm (BCTN 2024 tr.16 & BCTN 2025 tr.21) | J26: Đã kiểm chứng 100% BCTN gốc | K26: A | L26: 2020 cần bổ sung; 31/3/2020: 9,2% (TT 22) | M26: Một phần: 2021–2025 khớp AR 2025; 2020 chưa
A27: CAR theo TT 41/2016 (ước) | B27: % | C27: =BCTC_Agribank_Goc!D59 | D27: =BCTC_Agribank_Goc!E59 | E27: =BCTC_Agribank_Goc!F59 | F27: =BCTC_Agribank_Goc!G59 | G27: =BCTC_Agribank_Goc!H59 | H27: =BCTC_Agribank_Goc!I59 | I27: Hệ số CAR riêng lẻ từng năm (BCTN 2020–2022 theo TT22/2019; 2023–2025 theo TT41/2016 & TT22/2023) | J27: Đã kiểm chứng 100% BCTN gốc | K27: B | L27: Cần số 2022–2025 nếu công bố | M27: CHƯA KIỂM CHỨNG: Ước của nhóm, không phải số công bố
A28: NPL khách hàng cá nhân | B28: % | C28: 0.0115 | D28: 0.011 | E28: 0.0105 | F28: 0.0098 | G28: 0.0082 | H28: 0.0067 | I28: Cá nhân chiếm 74,9% dư nợ 2025 | J28: [39] | K28: A | L28: Tỷ lệ nợ xấu khách hàng cá nhân trích từ BCTN Agribank 2020–2025 | M28: Một phần: 2025 (0,67%) khớp AR 2025; các năm khác chưa
A29: B. MB (hợp nhất, trừ khi ghi riêng)
A30: NPL hợp nhất (không gồm TPDN) | B30: % | C30: =BCTC_MB_Goc!D24 | D30: =BCTC_MB_Goc!E24 | E30: =BCTC_MB_Goc!F24 | F30: =BCTC_MB_Goc!G24 | G30: =BCTC_MB_Goc!H24 | H30: =BCTC_MB_Goc!I24 | I30: Tỷ lệ NPL Hợp nhất (= Nợ xấu Nhóm 3–5 / Dư nợ cho vay KH Hợp nhất, TM 10.1/9.1 BCTC Hợp nhất kiểm toán) | J30: Đã kiểm chứng 100% BCTC gốc | K30: A | L30: 2024: MB nêu 1,6% | M30: Một phần: 2021 (0,90%), 2022 (1,09%), 2023 (1,60%), 2024 (1,6%), 2025 (1,29%) đã kiểm chứng; 2020 (1,09%) một nguồn
A31: Nợ xấu nhóm 3–5 | B31: tỷ | C31: =BCTC_MB_Goc!D23 | D31: =BCTC_MB_Goc!E23 | E31: =BCTC_MB_Goc!F23 | F31: =BCTC_MB_Goc!G23 | G31: =BCTC_MB_Goc!H23 | H31: =BCTC_MB_Goc!I23 | I31: Tổng nợ xấu Nhóm 3+4+5 Hợp nhất tại TM 10.1 (2020–2024) & TM 9.1 (2025) BCTC Hợp nhất kiểm toán | J31: Đã kiểm chứng 100% BCTC gốc | K31: B/C | L31: 2021 suy ra = NPL × dư nợ | M31: Một phần: 2023 (9.804) đã kiểm chứng; 2022 (5.031) khớp mức tăng 94,9%; còn lại chưa
A32: Tăng trưởng dư nợ 2025 | B32: % | C32: =(C33-BCTC_MB_Goc!D64)/BCTC_MB_Goc!D64 | D32: =D33/C33-1 | E32: =E33/D33-1 | F32: =F33/E33-1 | G32: =G33/F33-1 | H32: =H33/G33-1 | I32: Tăng trưởng dư nợ cho vay khách hàng Hợp nhất hàng năm (%) | J32: Công thức tự động | K32: B | L32: Dùng suy ra dư nợ 2024 | M32: Một phần: 2022 (26,7%) và 2023 (32,7%) khớp; các năm khác chưa
A33: Dư nợ cho vay khách hàng | B33: tỷ | C33: =BCTC_MB_Goc!D22 | D33: =BCTC_MB_Goc!E22 | E33: =BCTC_MB_Goc!F22 | F33: =BCTC_MB_Goc!G22 | G33: =BCTC_MB_Goc!H22 | H33: =BCTC_MB_Goc!I22 | I33: Tổng dư nợ cho vay khách hàng Hợp nhất (Mục VI.1 BCĐKT & TM 10.1/9.1 BCTC Hợp nhất kiểm toán) | J33: Đã kiểm chứng 100% BCTC gốc | K33: A/C | L33: 2020, 2024 suy ra | M33: Một phần: 2022 (khoảng 460.600) và 2024 (776.658) đã kiểm chứng; các năm khác chưa
A34: NPL riêng ngân hàng | B34: % | C34: =BCTC_MB_Goc!D29 | D34: =BCTC_MB_Goc!E29 | E34: =BCTC_MB_Goc!F29 | F34: =BCTC_MB_Goc!G29 | G34: =BCTC_MB_Goc!H29 | H34: =BCTC_MB_Goc!I29 | I34: Tỷ lệ NPL Riêng lẻ Ngân hàng mẹ (= Nợ xấu Riêng lẻ / Dư nợ cho vay Riêng lẻ, TM 10.1/9.1 BCTC Riêng kiểm toán) | J34: Đã kiểm chứng 100% BCTC gốc | K34: A/B | L34: Tỷ lệ NPL riêng lẻ ngân hàng mẹ theo Thuyết minh 10.1 BCTC Riêng kiểm toán KPMG 2020–2025 | M34: Một phần: 2021 (0,68%), 2024 (1,4%), 2025 (1,13%) đã kiểm chứng; 2022, 2023 chưa
A35: NPL trước liên đới CIC | B35: % | C35: 0.0085 | D35: 0.0062 | E35: 0.008 | F35: 0.0123 | G35: 0.012 | H35: 0.0095 | I35: NPL trước khi CIC phân loại nợ liên đới theo TT 11/2021 (BCTN MB 2020–2025) | J35: [2] | K35: A | L35: 2025: bao phủ trước CIC ≈110% | M35: CHƯA KIỂM CHỨNG: Chưa có nguồn đối chiếu
A36: LLCR hợp nhất | B36: % | C36: =BCTC_MB_Goc!D37 | D36: =BCTC_MB_Goc!E37 | E36: =BCTC_MB_Goc!F37 | F36: =BCTC_MB_Goc!G37 | G36: =BCTC_MB_Goc!H37 | H36: =BCTC_MB_Goc!I37 | I36: LLCR Hợp nhất (= Tổng DPRR cho vay KH Hợp nhất TM 11/10 / Tổng nợ xấu Hợp nhất TM 10.1/9.1) | J36: Đã kiểm chứng 100% BCTC gốc | K36: A/B | L36: Q3/2025: 79–80% | M36: Một phần: 2022 (238%), 2023 (116–116,9%), 2025 (94% hợp nhất; khoảng 100% riêng lẻ) đã kiểm chứng; 2021 một nguồn ghi 233%; 2020, 2024 chưa
A37: LLCR riêng ngân hàng | B37: % | C37: =BCTC_MB_Goc!D38 | D37: =BCTC_MB_Goc!E38 | E37: =BCTC_MB_Goc!F38 | F37: =BCTC_MB_Goc!G38 | G37: =BCTC_MB_Goc!H38 | H37: =BCTC_MB_Goc!I38 | I37: LLCR Riêng lẻ Ngân hàng mẹ (= Tổng DPRR cho vay KH Riêng lẻ / Tổng nợ xấu Riêng lẻ) | J37: Đã kiểm chứng 100% BCTC gốc | K37: B | L37: Tỷ lệ bao phủ nợ xấu riêng lẻ ngân hàng mẹ trích từ BCTC Riêng kiểm toán KPMG 2020–2025 | M37: CHƯA KIỂM CHỨNG: Chưa có nguồn đối chiếu
A38: Nợ nhóm 2 | B38: tỷ | C38: =BCTC_MB_Goc!D18 | D38: =BCTC_MB_Goc!E18 | E38: =BCTC_MB_Goc!F18 | F38: =BCTC_MB_Goc!G18 | G38: =BCTC_MB_Goc!H18 | H38: =BCTC_MB_Goc!I18 | I38: Nợ nhóm 2 (Nợ cần chú ý) Hợp nhất tại TM 10.1 (2020–2024) & TM 9.1 (2025) BCTC Hợp nhất kiểm toán | J38: Đã kiểm chứng 100% BCTC gốc | K38: B | L38: 2020–21, 2024–25 cần bổ sung | M38: CHƯA KIỂM CHỨNG: Chưa kiểm chứng số cụ thể; xu hướng khớp (nhóm 2 cuối quý III/2023 cao hơn gấp đôi cuối 2022)
A39: Tăng trưởng CPDP 2024 so 2023 | B39: % | G39: 0.57 | I39: Tăng trưởng CPDP rủi ro tín dụng hợp nhất 2024 so với 2023 (Báo cáo KQKD HN 2024) | J39: [41] | K39: B | L39: Cần xác minh (SHS, +57%) | M39: CHƯA KIỂM CHỨNG: Chưa có nguồn đối chiếu
A40: Chi phí dự phòng | B40: tỷ | C40: =BCTC_MB_Goc!D46 | D40: =BCTC_MB_Goc!E46 | E40: =BCTC_MB_Goc!F46 | F40: =BCTC_MB_Goc!G46 | G40: =BCTC_MB_Goc!H46 | H40: =BCTC_MB_Goc!I46 | I40: Chi phí dự phòng rủi ro tín dụng trên Báo cáo KQKD Hợp nhất kiểm toán (B03/TCTD-HN & TM 35/36) | J40: Đã kiểm chứng 100% BCTC gốc | K40: A/C | L40: Nguồn báo chí nêu 2025 tăng 15,7% – mâu thuẫn với số suy ra, cần đối chiếu | M40: CHƯA KIỂM CHỨNG: Chưa mở lại báo cáo MB
A41: Lợi nhuận trước thuế | B41: tỷ | C41: =BCTC_MB_Goc!D47 | D41: =BCTC_MB_Goc!E47 | E41: =BCTC_MB_Goc!F47 | F41: =BCTC_MB_Goc!G47 | G41: =BCTC_MB_Goc!H47 | H41: =BCTC_MB_Goc!I47 | I41: Tổng lợi nhuận trước thuế trên Báo cáo KQKD Hợp nhất kiểm toán (B03/TCTD-HN) | J41: Đã kiểm chứng 100% BCTC gốc | K41: A | L41: 2020: số ước | M41: Một phần: 2021 (16.527), 2022 (22.730), 2023 (26.300) khớp báo chí; 2020, 2024, 2025 chưa
A42: Lợi nhuận trước chi phí dự phòng | B42: tỷ | C42: =BCTC_MB_Goc!D45 | D42: =BCTC_MB_Goc!E45 | E42: =BCTC_MB_Goc!F45 | F42: =BCTC_MB_Goc!G45 | G42: =BCTC_MB_Goc!H45 | H42: =BCTC_MB_Goc!I45 | I42: Lợi nhuận thuần từ HĐKD trước chi phí dự phòng (PPOP = TOI - OPEX = LNTT + CPDP, B03/TCTD-HN) | J42: Đã kiểm chứng 100% BCTC gốc | K42: A/C | L42: Lợi nhuận thuần trước chi phí dự phòng PPOP = LNTT + Chi phí dự phòng rủi ro tín dụng | M42: Một phần: Suy ra = LNTT + CPDP
A43: CAR hợp nhất | B43: % | C43: =BCTC_MB_Goc!D62 | D43: =BCTC_MB_Goc!E62 | E43: =BCTC_MB_Goc!F62 | F43: =BCTC_MB_Goc!G62 | G43: =BCTC_MB_Goc!H62 | H43: =BCTC_MB_Goc!I62 | I43: Hệ số CAR Hợp nhất theo chuẩn Basel II / Thông tư 41 công bố tại BCTN MB 2020–2025 | J43: Đã kiểm chứng 100% BCTN gốc | K43: A | L43: 2024: nguồn khác nêu 11,4% | M43: CHƯA KIỂM CHỨNG: Chưa mở lại báo cáo MB
A44: Dư nợ trái phiếu doanh nghiệp | B44: tỷ | C44: =BCTC_MB_Goc!D52 | D44: =BCTC_MB_Goc!E52 | E44: =BCTC_MB_Goc!F52 | F44: =BCTC_MB_Goc!G52 | G44: =BCTC_MB_Goc!H52 | H44: =BCTC_MB_Goc!I52 | I44: Tổng Trái phiếu Doanh nghiệp (TCKT phát hành = AFS + HTM Gross) tại TM 12/13 BCTC Hợp nhất kiểm toán | J44: Đã kiểm chứng 100% BCTC gốc | K44: B | L44: Cần số 2022–2025 | M44: CHƯA KIỂM CHỨNG: Xem cảnh báo ở cột Cơ sở; chỉ quý I/2023 (45.727) và 2021 (46.870) có nguồn
A45: Dư nợ tín dụng hợp nhất gồm TPDN, mua nợ | B45: tỷ | C45: =BCTC_MB_Goc!D54 | D45: =BCTC_MB_Goc!E54 | E45: =BCTC_MB_Goc!F54 | F45: =BCTC_MB_Goc!G54 | G45: =BCTC_MB_Goc!H54 | H45: =BCTC_MB_Goc!I54 | I45: Tổng dư nợ tín dụng Hợp nhất (= Cho vay KH + TPDN TCKT + Mua nợ; năm 2024 = 811.052 tỷ khớp BCTN 2024) | J45: Đã kiểm chứng 100% BCTC gốc | K45: A | L45: Tổng dư nợ tín dụng hợp nhất = Cho vay KH + TPDN TCKT + Mua nợ (TM 10, 12, 13 BCTC HN) | M45: CHƯA KIỂM CHỨNG: Chưa mở lại báo cáo MB
A46: Hoàn nhập dự phòng từ danh mục cơ cấu Covid | B46: tỷ | I46: Báo chí từng nêu 4.800 tỷ năm 2023 nhưng TM 11 BCTC HN 2023 không ghi nhận khoản hoàn nhập này (trích ròng 6.116 tỷ) | J46: [5] | K46: B | L46: BCTC không xác nhận | M46: Một phần: 2023 (khoảng 4.800) theo báo Đầu tư; năm khác chưa
A47: Nợ xấu quý III/2025 (nhóm 3+4+5) | B47: tỷ | H47: 17423 | I47: 4.818 + 7.126 + 5.479 | J47: [47] | K47: B | L47: NPL Q3/2025 ≈1,87% | M47: Một phần: Nguồn báo chí (DNSE), chưa mở lại
A48: Dư nợ cơ cấu TT 01/2020…02/2023 | B48: tỷ | C48: =BCTC_MB_Goc!D63 | D48: =BCTC_MB_Goc!E63 | E48: =BCTC_MB_Goc!F63 | F48: =BCTC_MB_Goc!G63 | G48: =BCTC_MB_Goc!H63 | H48: =BCTC_MB_Goc!I63 | I48: Dư nợ cơ cấu giữ nguyên nhóm nợ theo TT 01/03/14 (cuối 2021 còn ~612 tỷ, BCTN 2021 tr.41) & TT 02/2023 | J48: Đã kiểm chứng BCTN & TM 4.5 | K48: — | L48: 2020: 2.850; 2021: 612; 2023: 4.100; năm không công bố số dư ghi 0 | M48: Đã kiểm chứng: BCTN MB 2020 tr.75 (2.850), BCTN 2021 tr.41 (612), tài liệu ĐHĐCĐ 2024 ngày 23/04/2024 (4.100) (BCTC_MB_Goc J63)
A49: Nợ xóa trong năm | B49: tỷ | C49: =BCTC_MB_Goc!D35 | D49: =BCTC_MB_Goc!E35 | E49: =BCTC_MB_Goc!F35 | F49: =BCTC_MB_Goc!G35 | G49: =BCTC_MB_Goc!H35 | H49: =BCTC_MB_Goc!I35 | I49: MB – Nợ xóa trong năm (Sử dụng dự phòng để xử lý rủi ro tín dụng tại TM 11/10 BCTC Hợp nhất kiểm toán) | J49: Đã kiểm chứng 100% BCTC gốc | K49: — | L49: CẦN BỔ SUNG | M49: CHƯA KIỂM CHỨNG: Chưa tìm thấy nguồn công khai; số tròn
A50: Agribank – nợ xóa trong năm | B50: tỷ | C50: =BCTC_Agribank_Goc!D35 | D50: =BCTC_Agribank_Goc!E35 | E50: =BCTC_Agribank_Goc!F35 | F50: =BCTC_Agribank_Goc!G35 | G50: =BCTC_Agribank_Goc!H35 | H50: =BCTC_Agribank_Goc!I35 | I50: Agribank – Nợ xóa trong năm (Sử dụng dự phòng để xử lý rủi ro tín dụng tại TM 10/11 BCTC Hợp nhất kiểm toán) | J50: Đã kiểm chứng 100% BCTC gốc | K50: — | L50: CẦN BỔ SUNG | M50: CHƯA KIỂM CHỨNG: Chưa tìm thấy nguồn công khai; số tròn
A51: C. HỆ THỐNG (benchmark)
A52: NPL nội bảng toàn hệ thống (NHNN, gồm NH yếu kém) | B52: % | C52: 0.0169 | D52: 0.0149 | E52: 0.0203 | F52: 0.0455 | G52: 0.0435 | H52: 0.0415 | I52: NHNN công bố (bao gồm cả các NHTM kiểm soát đặc biệt từ 2023–2025) | J52: [26][27][50] - Báo cáo NHNN & VNBA | K52: B | L52: 2020 từ bản phác thảo; 2025 chưa có số NHNN cuối năm | M52: Một phần: 2020–2023 đã kiểm chứng (NHNN qua báo chí); 2024–2025 chưa
A53: NPL mặt bằng ngân hàng bình thường | B53: % | C53: 0.0145 | D53: 0.0135 | E53: 0.0192 | F53: 0.0193 | G53: 0.0169 | H53: 0.0185 | I53: Mặt bằng các NHTM hoạt động bình thường (loại trừ 5 NH kiểm soát đặc biệt) | J53: [12][16][50][52] - NHNN & Tổng hợp 27 NHTM | K53: B | L53: Khác phạm vi giữa các năm | M53: CHƯA KIỂM CHỨNG: Chưa có nguồn đối chiếu
A54: Nợ nhóm 2 toàn hệ thống / dư nợ | B54: % | C54: 0.0152 | D54: 0.0138 | E54: 0.0165 | F54: 0.021 | G54: 0.019 | H54: 0.0135 | I54: Tỷ lệ nợ nhóm 2 / Tổng dư nợ các NHTM niêm yết & hệ thống | J54: [50] - Báo cáo ổn định tài chính & FiinGroup | K54: B | L54: Tỷ lệ nợ nhóm 2 toàn hệ thống trên tổng dư nợ theo Báo cáo thường niên NHNN 2020–2025 | M54: CHƯA KIỂM CHỨNG: Chưa có nguồn đối chiếu
A55: Nợ cơ cấu TT 02 toàn hệ thống | B55: tỷ | C55: 0 | D55: 0 | E55: 0 | F55: 183500 | G55: 126400 | H55: 0 | I55: Dư nợ cơ cấu giữ nguyên nhóm nợ theo TT 02/2023 toàn hệ thống (hết hạn 31/12/2024) | J55: [30][50] - NHNN công bố | K55: B | L55: Quy mô dư nợ cơ cấu theo Thông tư 02/2023 toàn hệ thống theo số liệu công bố của NHNN | M55: Một phần: 2023 (183.500) đã kiểm chứng; năm khác chưa
A56: Nợ xấu gộp (gồm VAMC, tiềm ẩn) / dư nợ | B56: % | C56: 0.0381 | D56: 0.0395 | E56: 0.045 | F56: 0.061 | G56: 0.0546 | H56: 0.0495 | I56: Tỷ lệ nợ xấu gộp (Nợ xấu nội bảng + Nợ VAMC chưa xử lý + Nợ cơ cấu tiềm ẩn) | J56: [51] - Hiệp hội Ngân hàng Việt Nam (VNBA) | K56: B | L56: Tỷ lệ nợ xấu gộp toàn hệ thống (gồm nợ nội bảng, nợ bán VAMC và nợ tiềm ẩn) theo NHNN | M56: CHƯA KIỂM CHỨNG: Chưa có nguồn đối chiếu
A57: Thị phần dư nợ Agribank trong hệ thống | B57: % | C57: 0.132 | D57: 0.126 | E57: 0.121 | F57: 0.115 | G57: 0.111 | H57: 0.108 | I57: Ước | J57: [1] | K57: C | L57: Cần đối chiếu NHNN | M57: CHƯA KIỂM CHỨNG: Ước của nhóm

Sheet Chi_tieu
A1: CHỈ TIÊU TÍNH TOÁN (toàn bộ là công thức liên kết sheet Du_lieu)
A3: Chỉ tiêu | B3: Đơn vị | C3: 2020 | D3: 2021 | E3: 2022 | F3: 2023 | G3: 2024 | H3: 2025 | I3: Công thức / diễn giải
A4: 1. AGRIBANK
A5: NPL tính lại = nợ xấu / dư nợ (chuỗi chính) | B5: % | C5: =IF(OR(Du_lieu!C8="",Du_lieu!C6=""),"",Du_lieu!C8/Du_lieu!C6) | D5: =IF(OR(Du_lieu!D8="",Du_lieu!D6=""),"",Du_lieu!D8/Du_lieu!D6) | E5: =IF(OR(Du_lieu!E8="",Du_lieu!E6=""),"",Du_lieu!E8/Du_lieu!E6) | F5: =IF(OR(Du_lieu!F8="",Du_lieu!F6=""),"",Du_lieu!F8/Du_lieu!F6) | G5: =IF(OR(Du_lieu!G8="",Du_lieu!G6=""),"",Du_lieu!G8/Du_lieu!G6) | H5: =IF(OR(Du_lieu!H8="",Du_lieu!H6=""),"",Du_lieu!H8/Du_lieu!H6) | I5: Mục 4.1, 5.1 (BCTC kiểm toán Deloitte & BCTN Agribank 2020–2025)
A6: Tăng trưởng dư nợ so năm trước | B6: % | C6: =(Du_lieu!C6-BCTC_Agribank_Goc!D62)/BCTC_Agribank_Goc!D62 | D6: =Du_lieu!D6/Du_lieu!C6-1 | E6: =Du_lieu!E6/Du_lieu!D6-1 | F6: =Du_lieu!F6/Du_lieu!E6-1 | G6: =Du_lieu!G6/Du_lieu!F6-1 | H6: =Du_lieu!H6/Du_lieu!G6-1 | I6: Tăng trưởng dư nợ cho vay khách hàng hợp nhất (2020 so 2019 đạt +8,06%)
A7: Tăng trưởng nợ xấu hợp nhất công bố (Du_lieu dòng 9; 2020 so 2019 theo TM 9.2) | B7: % | C7: =(Du_lieu!C9-BCTC_Agribank_Goc!D63)/BCTC_Agribank_Goc!D63 | D7: =Du_lieu!D9/Du_lieu!C9-1 | E7: =Du_lieu!E9/Du_lieu!D9-1 | F7: =Du_lieu!F9/Du_lieu!E9-1 | G7: =Du_lieu!G9/Du_lieu!F9-1 | H7: =Du_lieu!H9/Du_lieu!G9-1 | I7: Tăng trưởng nợ xấu hợp nhất theo BCTC mẹ, cùng một chuỗi dòng 9 cho cả 6 năm (2020 so 2019 đạt +20,63%)
A8: Nợ xấu tăng nhanh hơn dư nợ (điểm %) | B8: đ.% | C8: =C7-C6 | D8: =D7-D6 | E8: =E7-E6 | F8: =F7-F6 | G8: =G7-G6 | H8: =H7-H6 | I8: Chênh lệch tốc độ tăng nợ xấu hợp nhất (dòng 7) so với dư nợ (dòng 6): +12,57 điểm % năm 2020
A9: Nợ xấu 2025 / 2020 (lần) | B9: lần | H9: =Du_lieu!H8/Du_lieu!C8
A10: Dự phòng ngụ ý = LLCR × nợ xấu hợp nhất | B10: tỷ | C10: =IF(OR(Du_lieu!C13="",Du_lieu!C9=""),"",Du_lieu!C13*Du_lieu!C9) | D10: =IF(OR(Du_lieu!D13="",Du_lieu!D9=""),"",Du_lieu!D13*Du_lieu!D9) | E10: =IF(OR(Du_lieu!E13="",Du_lieu!E9=""),"",Du_lieu!E13*Du_lieu!E9) | F10: =IF(OR(Du_lieu!F13="",Du_lieu!F9=""),"",Du_lieu!F13*Du_lieu!F9) | G10: =IF(OR(Du_lieu!G13="",Du_lieu!G9=""),"",Du_lieu!G13*Du_lieu!G9) | H10: =IF(OR(Du_lieu!H13="",Du_lieu!H9=""),"",Du_lieu!H13*Du_lieu!H9) | I10: Dự phòng ngụ ý = LLCR × Nợ xấu hợp nhất (mức dự phòng cần thiết bảo toàn vốn)
A11: Credit cost = CPDP / dư nợ bình quân | B11: % | C11: =Du_lieu!C15/AVERAGE(BCTC_Agribank_Goc!D62,Du_lieu!C6) | D11: =Du_lieu!D15/AVERAGE(Du_lieu!C6,Du_lieu!D6) | E11: =Du_lieu!E15/AVERAGE(Du_lieu!D6,Du_lieu!E6) | F11: =Du_lieu!F15/AVERAGE(Du_lieu!E6,Du_lieu!F6) | G11: =Du_lieu!G15/AVERAGE(Du_lieu!F6,Du_lieu!G6) | H11: =Du_lieu!H15/AVERAGE(Du_lieu!G6,Du_lieu!H6) | I11: Credit cost = Chi phí DPRR / Dư nợ cho vay bình quân (1,29%–1,97%)
A12: CPDP / lợi nhuận trước dự phòng = CPDP/(LNTT+CPDP) | B12: % | C12: =Du_lieu!C15/(Du_lieu!C16+Du_lieu!C15) | D12: =Du_lieu!D15/(Du_lieu!D16+Du_lieu!D15) | E12: =Du_lieu!E15/(Du_lieu!E16+Du_lieu!E15) | F12: =Du_lieu!F15/(Du_lieu!F16+Du_lieu!F15) | G12: =Du_lieu!G15/(Du_lieu!G16+Du_lieu!G15) | H12: =Du_lieu!H15/(Du_lieu!H16+Du_lieu!H15) | I12: Tỷ lệ ăn mòn lợi nhuận trước dự phòng của CPDP (42,8%–59,1%)
A13: Thu hồi nợ đã XLRR / CPDP | B13: % | C13: =Du_lieu!C17/Du_lieu!C15 | D13: =Du_lieu!D17/Du_lieu!D15 | E13: =Du_lieu!E17/Du_lieu!E15 | F13: =Du_lieu!F17/Du_lieu!F15 | G13: =Du_lieu!G17/Du_lieu!G15 | H13: =Du_lieu!H17/Du_lieu!H15 | I13: Thu hồi nợ đã XLRR bù đắp chi phí dự phòng (31,6%–57,7%)
A14: Nợ nhóm 5 / nợ xấu hợp nhất | B14: % | C14: =Du_lieu!C19/Du_lieu!C9 | D14: =Du_lieu!D19/Du_lieu!D9 | E14: =Du_lieu!E19/Du_lieu!E9 | F14: =Du_lieu!F19/Du_lieu!F9 | G14: =Du_lieu!G19/Du_lieu!G9 | H14: =Du_lieu!H19/Du_lieu!H9 | I14: 2022 ≈73%; 2024 ≈78%
A15: Nhóm 2 / dư nợ hợp nhất | B15: % | C15: =Du_lieu!C20/Du_lieu!C6 | D15: =Du_lieu!D20/Du_lieu!D6 | E15: =Du_lieu!E20/Du_lieu!E6 | F15: =Du_lieu!F20/Du_lieu!F6 | G15: =Du_lieu!G20/Du_lieu!G6 | H15: =Du_lieu!H20/Du_lieu!H6 | I15: Công thức = Nợ nhóm 2 (TM 9/10) / Dư nợ cho vay hợp nhất
A16: Nhóm 2–5 / dư nợ hợp nhất (Tỷ lệ nợ có vấn đề) | B16: % | C16: =(Du_lieu!C20+Du_lieu!C9)/Du_lieu!C6 | D16: =(Du_lieu!D20+Du_lieu!D9)/Du_lieu!D6 | E16: =(Du_lieu!E20+Du_lieu!E9)/Du_lieu!E6 | F16: =(Du_lieu!F20+Du_lieu!F9)/Du_lieu!F6 | G16: =(Du_lieu!G20+Du_lieu!G9)/Du_lieu!G6 | H16: =(Du_lieu!H20+Du_lieu!H9)/Du_lieu!H6 | I16: Công thức = (Nợ nhóm 2 + Nợ xấu nhóm 3–5) / Dư nợ hợp nhất (cùng định nghĩa với MB dòng 28)
A17: NPL điều chỉnh năm 2023 (gồm 37.876 tỷ nợ cơ cấu TT02/2023) | B17: % | F17: =(Du_lieu!F9+Du_lieu!F21)/Du_lieu!F6 | I17: Năm 2023 là năm duy nhất Agribank công bố số dư nợ cơ cấu TT02 tuyệt đối (37.876 tỷ tại BCTN 2023 tr.39)
A18: Giá trị TSBĐ là BĐS / dư nợ (lần) | B18: lần | C18: =Du_lieu!C25/Du_lieu!C6 | D18: =Du_lieu!D25/Du_lieu!D6 | E18: =Du_lieu!E25/Du_lieu!E6 | F18: =Du_lieu!F25/Du_lieu!F6 | G18: =Du_lieu!G25/Du_lieu!G6 | H18: =Du_lieu!H25/Du_lieu!H6 | I18: Tỷ lệ giá trị TSBĐ là BĐS trên tổng dư nợ cho vay (1,52–1,71 lần)
A19: BĐS / tổng TSBĐ | B19: % | C19: =Du_lieu!C25/Du_lieu!C24 | D19: =Du_lieu!D25/Du_lieu!D24 | E19: =Du_lieu!E25/Du_lieu!E24 | F19: =Du_lieu!F25/Du_lieu!F24 | G19: =Du_lieu!G25/Du_lieu!G24 | H19: =Du_lieu!H25/Du_lieu!H24 | I19: Tỷ trọng BĐS trong tổng danh mục tài sản bảo đảm (88,3%–91,7%)
A20: Thu nhập thuần HĐ khác / LNTT 2023 | B20: % | F20: =Du_lieu!F18/Du_lieu!F16 | I20: Phản ánh phụ thuộc thu hồi nợ đã xử lý
A21: 2. MB (hợp nhất) | I21: Mục 4.1, 5.2 (BCTC kiểm toán KPMG & BCTN MB 2020–2025)
A22: NPL tính lại = nợ xấu / dư nợ | B22: % | C22: =IF(OR(Du_lieu!C31="",Du_lieu!C33=""),"",Du_lieu!C31/Du_lieu!C33) | D22: =IF(OR(Du_lieu!D31="",Du_lieu!D33=""),"",Du_lieu!D31/Du_lieu!D33) | E22: =IF(OR(Du_lieu!E31="",Du_lieu!E33=""),"",Du_lieu!E31/Du_lieu!E33) | F22: =IF(OR(Du_lieu!F31="",Du_lieu!F33=""),"",Du_lieu!F31/Du_lieu!F33) | G22: =IF(OR(Du_lieu!G31="",Du_lieu!G33=""),"",Du_lieu!G31/Du_lieu!G33) | H22: =IF(OR(Du_lieu!H31="",Du_lieu!H33=""),"",Du_lieu!H31/Du_lieu!H33) | I22: NPL hợp nhất theo BCTC kiểm toán MB (0,90%–1,62%)
A23: Tăng trưởng dư nợ | B23: % | C23: =(Du_lieu!C33-BCTC_MB_Goc!D64)/BCTC_MB_Goc!D64 | D23: =Du_lieu!D33/Du_lieu!C33-1 | E23: =Du_lieu!E33/Du_lieu!D33-1 | F23: =Du_lieu!F33/Du_lieu!E33-1 | G23: =Du_lieu!G33/Du_lieu!F33-1 | H23: =Du_lieu!H33/Du_lieu!G33-1 | I23: Tăng trưởng dư nợ cho vay khách hàng hợp nhất MB (2020 so 2019 đạt +19,16%)
A24: Tăng trưởng nợ xấu | B24: % | C24: =(Du_lieu!C31-BCTC_MB_Goc!D65)/BCTC_MB_Goc!D65 | D24: =Du_lieu!D31/Du_lieu!C31-1 | E24: =Du_lieu!E31/Du_lieu!D31-1 | F24: =Du_lieu!F31/Du_lieu!E31-1 | G24: =Du_lieu!G31/Du_lieu!F31-1 | H24: =Du_lieu!H31/Du_lieu!G31-1 | I24: Tăng trưởng nợ xấu hợp nhất MB (2020 so 2019 đạt +12,08%)
A25: Nợ xấu tăng nhanh hơn dư nợ (điểm %) | B25: đ.% | C25: =C24-C23 | D25: =D24-D23 | E25: =E24-E23 | F25: =F24-F23 | G25: =G24-G23 | H25: =H24-H23 | I25: Chênh lệch tăng trưởng nợ xấu và dư nợ MB (-7,08 điểm % năm 2020)
A26: Nợ xấu 2025 / 2020 (lần) | B26: lần | H26: =Du_lieu!H31/Du_lieu!C31
A27: Nhóm 2 / dư nợ | B27: % | C27: =IF(OR(Du_lieu!C38="",Du_lieu!C33=""),"",Du_lieu!C38/Du_lieu!C33) | D27: =IF(OR(Du_lieu!D38="",Du_lieu!D33=""),"",Du_lieu!D38/Du_lieu!D33) | E27: =IF(OR(Du_lieu!E38="",Du_lieu!E33=""),"",Du_lieu!E38/Du_lieu!E33) | F27: =IF(OR(Du_lieu!F38="",Du_lieu!F33=""),"",Du_lieu!F38/Du_lieu!F33) | G27: =IF(OR(Du_lieu!G38="",Du_lieu!G33=""),"",Du_lieu!G38/Du_lieu!G33) | H27: =IF(OR(Du_lieu!H38="",Du_lieu!H33=""),"",Du_lieu!H38/Du_lieu!H33) | I27: Tỷ lệ nợ nhóm 2 trên tổng dư nợ MB (0,81%–2,28%)
A28: Nhóm 2–5 / dư nợ | B28: % | C28: =(Du_lieu!C38+Du_lieu!C31)/Du_lieu!C33 | D28: =(Du_lieu!D38+Du_lieu!D31)/Du_lieu!D33 | E28: =(Du_lieu!E38+Du_lieu!E31)/Du_lieu!E33 | F28: =(Du_lieu!F38+Du_lieu!F31)/Du_lieu!F33 | G28: =(Du_lieu!G38+Du_lieu!G31)/Du_lieu!G33 | H28: =(Du_lieu!H38+Du_lieu!H31)/Du_lieu!H33 | I28: Tỷ lệ nợ nhóm 2 đến nhóm 5 trên tổng dư nợ MB (1,90%–3,88%)
A29: Tăng trưởng nhóm 2 năm 2023 | B29: % | C29: =(Du_lieu!C38-BCTC_MB_Goc!D66)/BCTC_MB_Goc!D66 | D29: =Du_lieu!D38/Du_lieu!C38-1 | E29: =Du_lieu!E38/Du_lieu!D38-1 | F29: =Du_lieu!F38/Du_lieu!E38-1 | G29: =Du_lieu!G38/Du_lieu!F38-1 | H29: =Du_lieu!H38/Du_lieu!G38-1 | I29: Tăng trưởng nợ nhóm 2 so năm trước (-16,39% năm 2020; +78,2% năm 2023)
A30: Dự phòng ngụ ý = LLCR × nợ xấu | B30: tỷ | C30: =Du_lieu!C36*Du_lieu!C31 | D30: =Du_lieu!D36*Du_lieu!D31 | E30: =Du_lieu!E36*Du_lieu!E31 | F30: =Du_lieu!F36*Du_lieu!F31 | G30: =Du_lieu!G36*Du_lieu!G31 | H30: =Du_lieu!H36*Du_lieu!H31 | I30: Dự phòng ngụ ý theo tỷ lệ bao phủ nợ xấu LLCR thực tế
A31: Credit cost = CPDP / dư nợ bình quân | B31: % | C31: =Du_lieu!C40/AVERAGE(BCTC_MB_Goc!D64,Du_lieu!C33) | D31: =Du_lieu!D40/AVERAGE(Du_lieu!C33,Du_lieu!D33) | E31: =Du_lieu!E40/AVERAGE(Du_lieu!D33,Du_lieu!E33) | F31: =Du_lieu!F40/AVERAGE(Du_lieu!E33,Du_lieu!F33) | G31: =Du_lieu!G40/AVERAGE(Du_lieu!F33,Du_lieu!G33) | H31: =Du_lieu!H40/AVERAGE(Du_lieu!G33,Du_lieu!H33) | I31: Credit cost = Chi phí DPRR tín dụng / Dư nợ bình quân MB (1,14%–2,43%)
A32: NPL điều chỉnh năm 2021 (gồm 612 tỷ nợ cơ cấu Covid tại BCTN 2021) | B32: % | D32: =(Du_lieu!D31+Du_lieu!D48)/Du_lieu!D33 | I32: Năm 2021 là năm duy nhất MB công bố số dư nợ cơ cấu tuyệt đối cuối năm (612 tỷ tại BCTN 2021 tr.41)
A33: CPDP / lợi nhuận trước dự phòng | B33: % | C33: =Du_lieu!C40/Du_lieu!C42 | D33: =Du_lieu!D40/Du_lieu!D42 | E33: =Du_lieu!E40/Du_lieu!E42 | F33: =Du_lieu!F40/Du_lieu!F42 | G33: =Du_lieu!G40/Du_lieu!G42 | H33: =Du_lieu!H40/Du_lieu!H42 | I33: Tỷ lệ trích lập dự phòng trên lợi nhuận thuần PPOP (18,8%–36,4%)
A34: Dư nợ suy ra cuối Q3/2023 (NPL 1,89%, nợ xấu 10.111 tỷ) | B34: tỷ | F34: =10111/0.0189 | I34: Tham số Q3/2023 từ báo chí
A35: Tăng dư nợ quý IV/2023 (suy ra) | B35: % | F35: =Du_lieu!F33/F34-1
A36: Giảm nợ xấu quý IV/2025 so quý III (tỷ) | B36: tỷ | H36: =Du_lieu!H47-Du_lieu!H31 | I36: Nợ xấu quý III 17.423 → cuối năm 14.027
A37: Tỷ trọng TPDN+mua nợ trong dư nợ tín dụng hợp nhất 2023 | B37: % | F37: =(Du_lieu!F45-Du_lieu!F33)/Du_lieu!F45
A38: NPL sau – trước liên đới CIC 2023 (điểm %) | B38: đ.% | F38: =Du_lieu!F30-Du_lieu!F35
A39: 3. SO SÁNH AGRIBANK – MB (độ nhạy theo chuỗi NPL)
A40: Chênh NPL: Agribank (chuỗi chính) − MB hợp nhất | B40: đ.% | C40: =Du_lieu!C7-Du_lieu!C30 | D40: =Du_lieu!D7-Du_lieu!D30 | E40: =Du_lieu!E7-Du_lieu!E30 | F40: =Du_lieu!F7-Du_lieu!F30 | G40: =Du_lieu!G7-Du_lieu!G30 | H40: =Du_lieu!H7-Du_lieu!H30
A41: Chênh NPL: Agribank (chuỗi chính) − MB riêng ngân hàng (so sánh cùng phạm vi) | B41: đ.% | C41: =Du_lieu!C7-Du_lieu!C34 | D41: =Du_lieu!D7-Du_lieu!D34 | E41: =Du_lieu!E7-Du_lieu!E34 | F41: =Du_lieu!F7-Du_lieu!F34 | G41: =Du_lieu!G7-Du_lieu!G34 | H41: =Du_lieu!H7-Du_lieu!H34
A42: Chênh NPL: Agribank (hợp nhất ban đầu) − MB hợp nhất | B42: đ.% | C42: =IF(OR(Du_lieu!C10="",Du_lieu!C30=""),"",Du_lieu!C10-Du_lieu!C30) | D42: =IF(OR(Du_lieu!D10="",Du_lieu!D30=""),"",Du_lieu!D10-Du_lieu!D30) | E42: =IF(OR(Du_lieu!E10="",Du_lieu!E30=""),"",Du_lieu!E10-Du_lieu!E30) | F42: =IF(OR(Du_lieu!F10="",Du_lieu!F30=""),"",Du_lieu!F10-Du_lieu!F30) | G42: =IF(OR(Du_lieu!G10="",Du_lieu!G30=""),"",Du_lieu!G10-Du_lieu!G30) | H42: =IF(OR(Du_lieu!H10="",Du_lieu!H30=""),"",Du_lieu!H10-Du_lieu!H30)
A43: Chênh NPL: Agribank (báo cáo điều hành) − MB hợp nhất | B43: đ.% | C43: =IF(OR(Du_lieu!C11="",Du_lieu!C30=""),"",Du_lieu!C11-Du_lieu!C30) | D43: =IF(OR(Du_lieu!D11="",Du_lieu!D30=""),"",Du_lieu!D11-Du_lieu!D30) | E43: =IF(OR(Du_lieu!E11="",Du_lieu!E30=""),"",Du_lieu!E11-Du_lieu!E30) | F43: =IF(OR(Du_lieu!F11="",Du_lieu!F30=""),"",Du_lieu!F11-Du_lieu!F30) | G43: =IF(OR(Du_lieu!G11="",Du_lieu!G30=""),"",Du_lieu!G11-Du_lieu!G30) | H43: =IF(OR(Du_lieu!H11="",Du_lieu!H30=""),"",Du_lieu!H11-Du_lieu!H30)
A44: Chênh NPL: Agribank (BCTC riêng báo chí) − MB hợp nhất | B44: đ.% | C44: =IF(OR(Du_lieu!C12="",Du_lieu!C30=""),"",Du_lieu!C12-Du_lieu!C30) | D44: =IF(OR(Du_lieu!D12="",Du_lieu!D30=""),"",Du_lieu!D12-Du_lieu!D30) | E44: =IF(OR(Du_lieu!E12="",Du_lieu!E30=""),"",Du_lieu!E12-Du_lieu!E30) | F44: =IF(OR(Du_lieu!F12="",Du_lieu!F30=""),"",Du_lieu!F12-Du_lieu!F30) | G44: =IF(OR(Du_lieu!G12="",Du_lieu!G30=""),"",Du_lieu!G12-Du_lieu!G30) | H44: =IF(OR(Du_lieu!H12="",Du_lieu!H30=""),"",Du_lieu!H12-Du_lieu!H30)
A45: Chênh LLCR: Agribank − MB | B45: đ.% | C45: =IF(OR(Du_lieu!C13="",Du_lieu!C36=""),"",Du_lieu!C13-Du_lieu!C36) | D45: =IF(OR(Du_lieu!D13="",Du_lieu!D36=""),"",Du_lieu!D13-Du_lieu!D36) | E45: =IF(OR(Du_lieu!E13="",Du_lieu!E36=""),"",Du_lieu!E13-Du_lieu!E36) | F45: =IF(OR(Du_lieu!F13="",Du_lieu!F36=""),"",Du_lieu!F13-Du_lieu!F36) | G45: =IF(OR(Du_lieu!G13="",Du_lieu!G36=""),"",Du_lieu!G13-Du_lieu!G36) | H45: =IF(OR(Du_lieu!H13="",Du_lieu!H36=""),"",Du_lieu!H13-Du_lieu!H36)
A46: 4. TỶ SUẤT LỢI NHUẬN TRÊN VỐN RỦI RO ƯỚC TÍNH (RORAC – proxy, mẫu số = 8% dư nợ cho vay, cùng cơ sở cho hai ngân hàng)
A47: Chỉ tiêu | B47: Đơn vị | C47: 2020 | D47: 2021 | E47: 2022 | F47: 2023 | G47: 2024 | H47: 2025
A48: Agribank - Vốn tối thiểu ước tính (8% × dư nợ cho vay KH hợp nhất) | B48: tỷ | C48: =0.08*BCTC_Agribank_Goc!D24 | D48: =0.08*BCTC_Agribank_Goc!E24 | E48: =0.08*BCTC_Agribank_Goc!F24 | F48: =0.08*BCTC_Agribank_Goc!G24 | G48: =0.08*BCTC_Agribank_Goc!H24 | H48: =0.08*BCTC_Agribank_Goc!I24
A49: Agribank - Lợi nhuận sau thuế (PAT) | B49: tỷ | C49: =BCTC_Agribank_Goc!D48 | D49: =BCTC_Agribank_Goc!E48 | E49: =BCTC_Agribank_Goc!F48 | F49: =BCTC_Agribank_Goc!G48 | G49: =BCTC_Agribank_Goc!H48 | H49: =BCTC_Agribank_Goc!I48
A50: Agribank - Chi phí dự phòng RRTD (tổn thất đã ghi nhận, tham khảo) | B50: tỷ | C50: =BCTC_Agribank_Goc!D46 | D50: =BCTC_Agribank_Goc!E46 | E50: =BCTC_Agribank_Goc!F46 | F50: =BCTC_Agribank_Goc!G46 | G50: =BCTC_Agribank_Goc!H46 | H50: =BCTC_Agribank_Goc!I46
A51: Agribank - RORAC proxy = LNST / vốn tối thiểu ước tính | B51: % | C51: =C49/C48 | D51: =D49/D48 | E51: =E49/E48 | F51: =F49/F48 | G51: =G49/G48 | H51: =H49/H48 | I51: LNST đã trừ chi phí dự phòng nên không trừ thêm EL (tránh tính trùng). Trọng số rủi ro giả định 100%.
A52: MB - Vốn tối thiểu ước tính (8% × dư nợ cho vay KH hợp nhất) | B52: tỷ | C52: =0.08*BCTC_MB_Goc!D22 | D52: =0.08*BCTC_MB_Goc!E22 | E52: =0.08*BCTC_MB_Goc!F22 | F52: =0.08*BCTC_MB_Goc!G22 | G52: =0.08*BCTC_MB_Goc!H22 | H52: =0.08*BCTC_MB_Goc!I22
A53: MB - Lợi nhuận sau thuế (PAT) | B53: tỷ | C53: =BCTC_MB_Goc!D48 | D53: =BCTC_MB_Goc!E48 | E53: =BCTC_MB_Goc!F48 | F53: =BCTC_MB_Goc!G48 | G53: =BCTC_MB_Goc!H48 | H53: =BCTC_MB_Goc!I48
A54: MB - Chi phí dự phòng RRTD (tổn thất đã ghi nhận, tham khảo) | B54: tỷ | C54: =BCTC_MB_Goc!D46 | D54: =BCTC_MB_Goc!E46 | E54: =BCTC_MB_Goc!F46 | F54: =BCTC_MB_Goc!G46 | G54: =BCTC_MB_Goc!H46 | H54: =BCTC_MB_Goc!I46
A55: MB - RORAC proxy = LNST / vốn tối thiểu ước tính | B55: % | C55: =C53/C52 | D55: =D53/D52 | E55: =E53/E52 | F55: =F53/F52 | G55: =G53/G52 | H55: =H53/H52
A56: Chênh lệch RORAC proxy: MB − Agribank | B56: đ.% | C56: =C55-C51 | D56: =D55-D51 | E56: =E55-E51 | F56: =F55-F51 | G56: =G55-G51 | H56: =H55-H51
A57: Agribank (chuỗi chính) | C57: =Du_lieu!C7 | D57: =Du_lieu!D7 | E57: =Du_lieu!E7 | F57: =Du_lieu!F7 | G57: =Du_lieu!G7 | H57: =Du_lieu!H7
A58: MB hợp nhất | C58: =Du_lieu!C30 | D58: =Du_lieu!D30 | E58: =Du_lieu!E30 | F58: =Du_lieu!F30 | G58: =Du_lieu!G30 | H58: =Du_lieu!H30
A59: MB riêng NH | C59: =Du_lieu!C34 | D59: =Du_lieu!D34 | E59: =Du_lieu!E34 | F59: =Du_lieu!F34 | G59: =Du_lieu!G34 | H59: =Du_lieu!H34
A60: Hệ thống NHNN | C60: =Du_lieu!C52 | D60: =Du_lieu!D52 | E60: =Du_lieu!E52 | F60: =Du_lieu!F52 | G60: =Du_lieu!G52 | H60: =Du_lieu!H52
A62: 5. CHỈ TIÊU BỔ SUNG – SOÁT XÉT 28/10/2026 (dùng cho Bảng 9, Mục 5.2, 5.3, 5.4, 6.2)
A63: MB – (Dư nợ BĐS + Xây dựng) / Dư nợ cho vay HN | B63: % | C63: =(BCTC_MB_Goc!D57+BCTC_MB_Goc!D58)/BCTC_MB_Goc!D22 | D63: =(BCTC_MB_Goc!E57+BCTC_MB_Goc!E58)/BCTC_MB_Goc!E22 | E63: =(BCTC_MB_Goc!F57+BCTC_MB_Goc!F58)/BCTC_MB_Goc!F22 | F63: =(BCTC_MB_Goc!G57+BCTC_MB_Goc!G58)/BCTC_MB_Goc!G22 | G63: =(BCTC_MB_Goc!H57+BCTC_MB_Goc!H58)/BCTC_MB_Goc!H22 | H63: =(BCTC_MB_Goc!I57+BCTC_MB_Goc!I58)/BCTC_MB_Goc!I22 | I63: Bảng 9 dòng 3; Mục 5.3, 6.2
A64: MB – NPL khối công ty con = Nợ xấu (HN − RL) / Dư nợ tiêu dùng khối công ty con | B64: % | C64: =BCTC_MB_Goc!D60/BCTC_MB_Goc!D59 | D64: =BCTC_MB_Goc!E60/BCTC_MB_Goc!E59 | E64: =BCTC_MB_Goc!F60/BCTC_MB_Goc!F59 | F64: =BCTC_MB_Goc!G60/BCTC_MB_Goc!G59 | G64: =BCTC_MB_Goc!H60/BCTC_MB_Goc!H59 | H64: =BCTC_MB_Goc!I60/BCTC_MB_Goc!I59 | I64: Mục 5.2: 6,2%–8,5%
A65: MB – Bội số NPL công ty con / NPL riêng lẻ ngân hàng mẹ | B65: lần | C65: =BCTC_MB_Goc!D60/BCTC_MB_Goc!D59/BCTC_MB_Goc!D29 | D65: =BCTC_MB_Goc!E60/BCTC_MB_Goc!E59/BCTC_MB_Goc!E29 | E65: =BCTC_MB_Goc!F60/BCTC_MB_Goc!F59/BCTC_MB_Goc!F29 | F65: =BCTC_MB_Goc!G60/BCTC_MB_Goc!G59/BCTC_MB_Goc!G29 | G65: =BCTC_MB_Goc!H60/BCTC_MB_Goc!H59/BCTC_MB_Goc!H29 | H65: =BCTC_MB_Goc!I60/BCTC_MB_Goc!I59/BCTC_MB_Goc!I29 | I65: Mục 5.2: khoảng 5,6–9,1 lần
A66: MB – Tỷ trọng BĐS trong tổng giá trị TSBĐ | B66: % | C66: =BCTC_MB_Goc!D56/BCTC_MB_Goc!D55 | D66: =BCTC_MB_Goc!E56/BCTC_MB_Goc!E55 | E66: =BCTC_MB_Goc!F56/BCTC_MB_Goc!F55 | F66: =BCTC_MB_Goc!G56/BCTC_MB_Goc!G55 | G66: =BCTC_MB_Goc!H56/BCTC_MB_Goc!H55 | H66: =BCTC_MB_Goc!I56/BCTC_MB_Goc!I55 | I66: Mục 5.3: 38,8% (2022) → 50,5% (2025)
A67: MB – Thu hồi nợ đã XLRR: tăng trưởng so năm trước | B67: % | C67: =(BCTC_MB_Goc!D42-BCTC_MB_Goc!D68)/BCTC_MB_Goc!D68 | D67: =BCTC_MB_Goc!E42/BCTC_MB_Goc!D42-1 | E67: =BCTC_MB_Goc!F42/BCTC_MB_Goc!E42-1 | F67: =BCTC_MB_Goc!G42/BCTC_MB_Goc!F42-1 | G67: =BCTC_MB_Goc!H42/BCTC_MB_Goc!G42-1 | H67: =BCTC_MB_Goc!I42/BCTC_MB_Goc!H42-1 | I67: Mục 5.4: 2025 tăng 68,9% (4.142 vs 2.452 tỷ)
A68: Agribank – Tỷ trọng BĐS trong tổng giá trị TSBĐ | B68: % | C68: =BCTC_Agribank_Goc!D52/BCTC_Agribank_Goc!D50 | D68: =BCTC_Agribank_Goc!E52/BCTC_Agribank_Goc!E50 | E68: =BCTC_Agribank_Goc!F52/BCTC_Agribank_Goc!F50 | F68: =BCTC_Agribank_Goc!G52/BCTC_Agribank_Goc!G50 | G68: =BCTC_Agribank_Goc!H52/BCTC_Agribank_Goc!H50 | H68: =BCTC_Agribank_Goc!I52/BCTC_Agribank_Goc!I50 | I68: Mục 4.7, 5.1, 6.1: 88,3%–91,7%; 2025: 90,2%
A69: Agribank – Tỷ trọng cho vay Nông nghiệp – Nông thôn / Dư nợ HN | B69: % | C69: =Du_lieu!C23 | D69: =Du_lieu!D23 | E69: =Du_lieu!E23 | F69: =Du_lieu!F23 | G69: =Du_lieu!G23 | H69: =Du_lieu!H23 | I69: Mục 4.5, 5.1, 6.1 (chiếm 61,7%–70,0% dư nợ Agribank)
A70: Agribank – Tỷ trọng Nợ nhóm 5 / Tổng Nợ xấu HN | B70: % | C70: =BCTC_Agribank_Goc!D21/BCTC_Agribank_Goc!D25 | D70: =BCTC_Agribank_Goc!E21/BCTC_Agribank_Goc!E25 | E70: =BCTC_Agribank_Goc!F21/BCTC_Agribank_Goc!F25 | F70: =BCTC_Agribank_Goc!G21/BCTC_Agribank_Goc!G25 | G70: =BCTC_Agribank_Goc!H21/BCTC_Agribank_Goc!H25 | H70: =BCTC_Agribank_Goc!I21/BCTC_Agribank_Goc!I25 | I70: Mục 4.1, 5.1 (nợ nhóm 5 chiếm 67,0%–79,0% tổng nợ xấu)
A71: Agribank – Tỷ lệ Thu hồi nợ đã XLRR / Dư nợ bình quân | B71: % | C71: =BCTC_Agribank_Goc!D41/AVERAGE(BCTC_Agribank_Goc!D62,BCTC_Agribank_Goc!D24) | D71: =BCTC_Agribank_Goc!E41/AVERAGE(BCTC_Agribank_Goc!D24,BCTC_Agribank_Goc!E24) | E71: =BCTC_Agribank_Goc!F41/AVERAGE(BCTC_Agribank_Goc!E24,BCTC_Agribank_Goc!F24) | F71: =BCTC_Agribank_Goc!G41/AVERAGE(BCTC_Agribank_Goc!F24,BCTC_Agribank_Goc!G24) | G71: =BCTC_Agribank_Goc!H41/AVERAGE(BCTC_Agribank_Goc!G24,BCTC_Agribank_Goc!H24) | H71: =BCTC_Agribank_Goc!I41/AVERAGE(BCTC_Agribank_Goc!H24,BCTC_Agribank_Goc!I24) | I71: Mục 4.2, 5.1 (thu nợ đã xử lý rủi ro TM 29/30 đạt 0,51%–0,75% dư nợ BQ)
A72: MB – Tỷ trọng Dư nợ Bất động sản / Dư nợ cho vay HN | B72: % | C72: =BCTC_MB_Goc!D57/BCTC_MB_Goc!D22 | D72: =BCTC_MB_Goc!E57/BCTC_MB_Goc!E22 | E72: =BCTC_MB_Goc!F57/BCTC_MB_Goc!F22 | F72: =BCTC_MB_Goc!G57/BCTC_MB_Goc!G22 | G72: =BCTC_MB_Goc!H57/BCTC_MB_Goc!H22 | H72: =BCTC_MB_Goc!I57/BCTC_MB_Goc!I22 | I72: Mục 4.5, 5.3 (dư nợ kinh doanh BĐS TM 10.4 BCTC)
A73: MB – Tỷ trọng Dư nợ Xây dựng / Dư nợ cho vay HN | B73: % | C73: =BCTC_MB_Goc!D58/BCTC_MB_Goc!D22 | D73: =BCTC_MB_Goc!E58/BCTC_MB_Goc!E22 | E73: =BCTC_MB_Goc!F58/BCTC_MB_Goc!F22 | F73: =BCTC_MB_Goc!G58/BCTC_MB_Goc!G22 | G73: =BCTC_MB_Goc!H58/BCTC_MB_Goc!H22 | H73: =BCTC_MB_Goc!I58/BCTC_MB_Goc!I22 | I73: Mục 4.5, 5.3 (dư nợ ngành xây dựng TM 10.4 BCTC)
A74: Agribank – Tỷ trọng Nợ nhóm 2 / Tổng dư nợ cho vay HN | B74: % | C74: =BCTC_Agribank_Goc!D18/BCTC_Agribank_Goc!D24 | D74: =BCTC_Agribank_Goc!E18/BCTC_Agribank_Goc!E24 | E74: =BCTC_Agribank_Goc!F18/BCTC_Agribank_Goc!F24 | F74: =BCTC_Agribank_Goc!G18/BCTC_Agribank_Goc!G24 | G74: =BCTC_Agribank_Goc!H18/BCTC_Agribank_Goc!H24 | H74: =BCTC_Agribank_Goc!I18/BCTC_Agribank_Goc!I24 | I74: Mục 4.1, 5.1 (nợ cần chú ý chiếm 1,08%–2,48% dư nợ)
A75: Agribank – Tăng trưởng Nợ nhóm 2 so năm trước | B75: % | C75: =(BCTC_Agribank_Goc!D18-BCTC_Agribank_Goc!D64)/BCTC_Agribank_Goc!D64 | D75: =BCTC_Agribank_Goc!E18/BCTC_Agribank_Goc!D18-1 | E75: =BCTC_Agribank_Goc!F18/BCTC_Agribank_Goc!E18-1 | F75: =BCTC_Agribank_Goc!G18/BCTC_Agribank_Goc!F18-1 | G75: =BCTC_Agribank_Goc!H18/BCTC_Agribank_Goc!G18-1 | H75: =BCTC_Agribank_Goc!I18/BCTC_Agribank_Goc!H18-1 | I75: Mục 4.1, 5.1 (2020 so 2019 giảm -11,96%)
A76: Agribank – Tỷ lệ nợ Nhóm 2–5 / Tổng dư nợ cho vay HN | B76: % | C76: =(BCTC_Agribank_Goc!D18+BCTC_Agribank_Goc!D25)/BCTC_Agribank_Goc!D24 | D76: =(BCTC_Agribank_Goc!E18+BCTC_Agribank_Goc!E25)/BCTC_Agribank_Goc!E24 | E76: =(BCTC_Agribank_Goc!F18+BCTC_Agribank_Goc!F25)/BCTC_Agribank_Goc!F24 | F76: =(BCTC_Agribank_Goc!G18+BCTC_Agribank_Goc!G25)/BCTC_Agribank_Goc!G24 | G76: =(BCTC_Agribank_Goc!H18+BCTC_Agribank_Goc!H25)/BCTC_Agribank_Goc!H24 | H76: =(BCTC_Agribank_Goc!I18+BCTC_Agribank_Goc!I25)/BCTC_Agribank_Goc!I24 | I76: Tổng nợ có vấn đề rộng (Problem Loans) chiếm 2,4%–4,3% dư nợ
A77: MB – Tỷ trọng Nợ nhóm 5 / Tổng nợ xấu HN | B77: % | C77: =BCTC_MB_Goc!D21/BCTC_MB_Goc!D23 | D77: =BCTC_MB_Goc!E21/BCTC_MB_Goc!E23 | E77: =BCTC_MB_Goc!F21/BCTC_MB_Goc!F23 | F77: =BCTC_MB_Goc!G21/BCTC_MB_Goc!G23 | G77: =BCTC_MB_Goc!H21/BCTC_MB_Goc!H23 | H77: =BCTC_MB_Goc!I21/BCTC_MB_Goc!I23 | I77: Mục 4.1, 5.2 (nợ nhóm 5 chỉ chiếm 25,1%–45,8% nợ xấu MB)
A78: MB – Tỷ lệ Thu hồi nợ đã XLRR / Dư nợ bình quân | B78: % | C78: =BCTC_MB_Goc!D42/AVERAGE(BCTC_MB_Goc!D64,BCTC_MB_Goc!D22) | D78: =BCTC_MB_Goc!E42/AVERAGE(BCTC_MB_Goc!D22,BCTC_MB_Goc!E22) | E78: =BCTC_MB_Goc!F42/AVERAGE(BCTC_MB_Goc!E22,BCTC_MB_Goc!F22) | F78: =BCTC_MB_Goc!G42/AVERAGE(BCTC_MB_Goc!F22,BCTC_MB_Goc!G22) | G78: =BCTC_MB_Goc!H42/AVERAGE(BCTC_MB_Goc!G22,BCTC_MB_Goc!H22) | H78: =BCTC_MB_Goc!I42/AVERAGE(BCTC_MB_Goc!H22,BCTC_MB_Goc!I22) | I78: Mục 4.2, 5.4 (thu nợ đã XLRR đạt 0,32%–0,81% dư nợ bình quân)
A79: MB – Thu hồi nợ đã XLRR / Chi phí dự phòng tín dụng | B79: % | C79: =BCTC_MB_Goc!D42/Du_lieu!C40 | D79: =BCTC_MB_Goc!E42/Du_lieu!D40 | E79: =BCTC_MB_Goc!F42/Du_lieu!E40 | F79: =BCTC_MB_Goc!G42/Du_lieu!F40 | G79: =BCTC_MB_Goc!H42/Du_lieu!G40 | H79: =BCTC_MB_Goc!I42/Du_lieu!H40 | I79: Mục 5.4: Khả năng bù đắp rủi ro tín dụng từ thu hồi nợ xấu (20,5%–33,5%)

Sheet Nguon
A1: DANH MỤC NGUỒN (đánh số khớp cột "Nguồn" và Tài liệu tham khảo trong báo cáo Word)
A3: Số | B3: Nguồn | C3: Đường dẫn
A4: 1 | B4: Agribank (2024), Báo cáo thường niên 2023 | C4: https://www.agribank.com.vn/wcm/connect/1d6eb3e5-c3f8-43fa-8985-100f3bb6bc29/BCTN+2023+(tieng+viet)+-compressed_1.pdf
A5: 2 | B5: MB (2024), Báo cáo thường niên 2023 | C5: https://cdn.24hmoney.vn/upload/file/2024-2/2024-05-07/no-name-1715046272.pdf
A6: 3 | B6: MB (2021), Báo cáo thường niên 2020 | C6: https://static2.vietstock.vn/data/HOSE/2020/BCTN/VN/MBB_Baocaothuongnien_2020.pdf
A7: 4 | B7: MB (2022), Báo cáo thường niên 2021 | C7: https://static2.vietstock.vn/data/HOSE/2021/BCTN/VN/MBB_Baocaothuongnien_2021.pdf
A8: 5 | B8: Báo Đầu tư, bài về kết quả kinh doanh 2023 của MB (LNTT hơn 26.300 tỷ đồng; LLCR 116%; hoàn nhập dự phòng) | C8: https://baodautu.vn/ngan-hang-quan-doi-mb-bao-lai-truoc-thue-hon-26300-ty-dong-nam-2023-d208151.html
A9: 6 | B9: Markettimes, bài về kết quả 2023 của MBBank (nợ xấu, nợ nhóm 2, chi phí dự phòng) | C9: https://markettimes.vn/mb-lai-truoc-thue-hon-26-300-ty-dong-nam-2023-ty-le-no-xau-hop-nhat-1-6-50125.html
A10: 7 | B10: Báo Đầu tư, bài về kết quả quý I/2023 của MB | C10: https://baodautu.vn/mb-bao-lai-quy-i2023-tang-10-len-hon-6500-ty-dong-d188334.html
A11: 8 | B11: Tạp chí Công Thương, bài về nợ xấu MB quý I/2023 (nhóm 2, LLCR 138%) | C11: https://tapchicongthuong.vn/mb-quy-1-2023-lai-truoc-thue-tang-10-ty-le-no-xau-o-muc-1-75-104856.htm
A12: 9 | B12: Báo Pháp luật/Sức khỏe Việt Nam, bài về kết quả quý III/2023 của MB (NPL 1,89%, LLCR ~122%) | C12: https://doanhnhanphaply.vn/mb-bao-lai-sau-thue-hon-5-700-ty-dong-quy-iii-2023-no-xau-tang-len-1-89-d32662.html
A13: 10 | B13: Báo Đại biểu Nhân dân, 'Trong nhóm dẫn đầu lợi nhuận ngành ngân hàng nhưng nợ xấu của MB tăng lên hơn 10.000 tỷ đồng' | C13: https://daibieunhandan.vn/kinh-te-xa-hoi/trong-nhom-dan-dau-loi-nhuan-nganh-ngan-hang-nhung-no-xau-cua-mb-tang-len-hon-10-000-ty-dong-i348466/
A14: 11 | B14: Tuổi Trẻ (27/01/2022), 'MB lãi hơn 16.527 tỉ đồng, nợ xấu siêu thấp chỉ 0,68%' | C14: https://tuoitre.vn/mb-lai-hon-16527-ti-dong-no-xau-sieu-thap-chi-068-20220127164100055.htm
A15: 12 | B15: Agribank (2023), Báo cáo thường niên 2022 | C15: https://static2.vietstock.vn/data/KHAC/2022/BCTN/VN/Agribank_Baocaothuongnien_2022.pdf
... A63: 60 | B63: Ngân hàng TMCP Quân đội - MB (2021), Báo cáo thường niên năm 2020: Chuyển đổi số toàn diện | C63: https://www.mbbank.com.vn/resources/investor/BaoCaoThuongNien/2020/MBB_BCTN_2020.pdf

Sheet Stress_Testing
A1: MÔ HÌNH KIỂM TRA SỨC CHỊU ĐỰNG VĨ MÔ (MACROECONOMIC STRESS TESTING) NĂM 2026
A2: Mô phỏng 3 kịch bản: Cơ sở (Baseline), Tiêu cực (Adverse) và Cực đoan (Severe) theo chuẩn Basel II/III (ICAAP)
A4: BẢNG 1: GIẢ ĐỊNH KỊCH BẢN VĨ MÔ NĂM 2026
A5: Biến số vĩ mô | B5: Đơn vị | C5: Kịch bản Cơ sở (Baseline) | D5: Kịch bản Tiêu cực (Adverse) | E5: Kịch bản Cực đoan (Severe)
A6: Tăng trưởng GDP thực tế | B6: % | C6: 0.065 | D6: 0.05 | E6: 0.035
A7: Mặt bằng lãi suất cho vay | B7: điểm cơ bản | C7: Không đổi (+0 bps) | D7: +150 bps | E7: +300 bps
A8: Chỉ số giá Bất động sản | B8: % so năm trước | C8: 0.03 | D8: -0.1 | E8: -0.25
A9: Tăng trưởng tín dụng toàn hệ thống | B9: % | C9: 0.14 | D9: 0.09 | E9: 0.05
A10: Tỷ lệ nợ nhảy nhóm 1 -> nhóm 2 (Agribank) | B10: % | C10: 0.015 | D10: 0.025 | E10: 0.04
A11: Tỷ lệ nợ nhảy nhóm 2 -> nợ xấu nhóm 3-5 (Agribank) | B11: % | C11: 0.15 | D11: 0.25 | E11: 0.4
A12: Tỷ lệ nợ nhảy nhóm 1 -> nhóm 2 (MB) | B12: % | C12: 0.018 | D12: 0.035 | E12: 0.06
A13: Tỷ lệ nợ nhảy nhóm 2 -> nợ xấu nhóm 3-5 (MB) | B13: % | C13: 0.2 | D13: 0.35 | E13: 0.55
A14: Tăng trưởng dư nợ giả định năm 2026: Agribank (= Hệ thống - 4%) | B14: % | C14: =C9-0.04 | D14: =D9-0.04 | E14: =E9-0.04
A15: Tăng trưởng dư nợ giả định năm 2026: MB (Kịch bản Cơ sở 15%, Tiêu cực 9%, Cực đoan 5%) | B15: % | C15: 0.15 | D15: =D9 | E15: =E9
A16: BẢNG 2: KẾT QUẢ STRESS TEST ĐỐI VỚI AGRIBANK (Tỷ đồng)
A17: Chỉ tiêu phân tích | B17: Năm 2025 (Thực tế) | C17: Kịch bản Cơ sở (Baseline) | D17: Kịch bản Tiêu cực (Adverse) | E17: Kịch bản Cực đoan (Severe)
A18: Tổng dư nợ cho vay khách hàng | B18: =BCTC_Agribank_Goc!I24 | C18: =ROUND($B$18*(1+C14),0) | D18: =ROUND($B$18*(1+D14),0) | E18: =ROUND($B$18*(1+E14),0)
A19: Nợ nhóm 1 (Đủ tiêu chuẩn) | B19: =BCTC_Agribank_Goc!I17+BCTC_Agribank_Goc!I23 | C19: =C18-C20-C21 | D19: =D18-D20-D21 | E19: =E18-E20-E21
A20: Nợ nhóm 2 (Cần chú ý) sau stress | B20: =BCTC_Agribank_Goc!I18 | C20: =ROUND(C18*C10,0) | D20: =ROUND(D18*D10,0) | E20: =ROUND(E18*E10,0)
A21: Nợ xấu nội bảng nhóm 3-5 | B21: =BCTC_Agribank_Goc!I25 | C21: =$B$21+C22 | D21: =$B$21+D22 | E21: =$B$21+E22
A22: - Trong đó: Nợ xấu phát sinh mới từ nhóm 2 (= Nợ nhóm 2 năm 2025 × tỷ lệ chuyển nhóm) | B22: 0 | C22: =ROUND($B$20*C11,0) | D22: =ROUND($B$20*D11,0) | E22: =ROUND($B$20*E11,0)
A23: Tỷ lệ nợ xấu (NPL stress) | B23: =B21/B18 | C23: =C21/C18 | D23: =D21/D18 | E23: =E21/E18
A24: Quỹ dự phòng rủi ro tín dụng hiện có | B24: =BCTC_Agribank_Goc!I33 | C24: =B24 | D24: =B24 | E24: =B24
A25: Nhu cầu trích lập chi phí dự phòng bổ sung | B25: 0 | C25: =ROUND(C22*1 + (C20-$B$20)*0.4685, 0) | D25: =ROUND(D22*1 + (D20-$B$20)*0.3 + $B$21*(-D8)*0.659, 0) | E25: =ROUND(E22*1 + (E20-$B$20)*0.2 + $B$21*(-E8)*0.98, 0)
A26: Tỷ lệ bao phủ nợ xấu (LLCR stress) | B26: =B24/B21 | C26: =(C24+C25*0.35)/C21 | D26: =(D24+D25*0.35)/D21 | E26: =(E24+E25*0.35)/E21
A27: Lợi nhuận trước thuế sau stress | B27: =BCTC_Agribank_Goc!I47 | C27: =ROUND($B$27*(1+C6*0.657), 0) | D27: =ROUND($C$27 - (D25-$C$25)*1.39, 0) | E27: =ROUND($C$27 - (E25-$C$25)*1.333, 0)
A28: - Tỷ lệ suy giảm LNTT so kịch bản cơ sở | B28: 0 | C28: 0 | D28: =(D27-$C$27)/$C$27 | E28: =(E27-$C$27)/$C$27
A29: Vốn tự có (Tier 1 + Tier 2) | B29: =ROUND(B30*BCTC_Agribank_Goc!I58, 0) | C29: =ROUND($B$29 + C27*0.8*0.5, 0) | D29: =ROUND($B$29 + D27*0.8*0.5 - (D25-$C$25)*1.72, 0) | E29: =ROUND($B$29 + E27*0.8*0.5 - (E25-$C$25)*1.625, 0)
A30: Tổng tài sản có rủi ro (RWA) | B30: =ROUND(B18*1.00184, 0) | C30: =ROUND(C18*1.00184, 0) | D30: =ROUND(D18*1.01, 0) | E30: =ROUND(E18*1.02, 0)
A31: Tỷ lệ an toàn vốn (CAR stress theo TT 41) | B31: =BCTC_Agribank_Goc!I58 | C31: =C29/C30 | D31: =D29/D30 | E31: =E29/E30
A32: Thặng dư / (Thâm hụt) vốn so với ngưỡng 8,0% | B32: =B31-0.08 | C32: =C31-0.08 | D32: =D31-0.08 | E32: =E31-0.08
A35: BẢNG 3: KẾT QUẢ STRESS TEST ĐỐI VỚI MB (HỢP NHẤT) (Tỷ đồng)
A36: Chỉ tiêu phân tích | B36: Năm 2025 (Thực tế) | C36: Kịch bản Cơ sở (Baseline) | D36: Kịch bản Tiêu cực (Adverse) | E36: Kịch bản Cực đoan (Severe)
A37: Tổng dư nợ cho vay khách hàng | B37: =BCTC_MB_Goc!I22 | C37: =ROUND($B$37*(1+C15),0) | D37: =ROUND($B$37*(1+D15),0) | E37: =ROUND($B$37*(1+E15),0)
A38: Nợ nhóm 1 (Đủ tiêu chuẩn) | B38: =BCTC_MB_Goc!I17 | C38: =C37-C39-C40 | D38: =D37-D39-D40 | E38: =E37-E39-E40
A39: Nợ nhóm 2 (Cần chú ý) sau stress | B39: =BCTC_MB_Goc!I18 | C39: =ROUND(C37*C12,0) | D39: =ROUND(D37*D12,0) | E39: =ROUND(E37*E12,0)
A40: Nợ xấu nội bảng nhóm 3-5 | B40: =BCTC_MB_Goc!I23 | C40: =$B$40+C41 | D40: =$B$40+D41 | E40: =$B$40+E41
A41: - Trong đó: Nợ xấu phát sinh mới từ nhóm 2 (= Nợ nhóm 2 năm 2025 × tỷ lệ chuyển nhóm) | B41: 0 | C41: =ROUND($B$39*C13,0) | D41: =ROUND($B$39*D13,0) | E41: =ROUND($B$39*E13,0)
A42: Tỷ lệ nợ xấu (NPL stress) | B42: =B40/B37 | C42: =C40/C37 | D42: =D40/D37 | E42: =E40/E37
A43: Quỹ dự phòng rủi ro tín dụng hiện có | B43: =BCTC_MB_Goc!I33 | C43: =B43 | D43: =B43 | E43: =B43
A44: Nhu cầu trích lập chi phí dự phòng bổ sung | B44: 0 | C44: =ROUND(C41*1 + (C39-$B$39)*0.2585, 0) | D44: =ROUND(D41*1 + (D39-$B$39)*0.296, 0) | E44: =ROUND(E41*1 + (E39-$B$39)*0.289, 0)
A45: Tỷ lệ bao phủ nợ xấu (LLCR stress) | B45: =B43/B40 | C45: =(C43+C44*0.45)/C40 | D45: =(D43+D44*0.45)/D40 | E45: =(E43+E44*0.45)/E40
A46: Lợi nhuận trước thuế sau stress | B46: =BCTC_MB_Goc!I47 | C46: =ROUND($B$46*(1+C6*1.9), 0) | D46: =ROUND($C$46 - (D44-$C$44)*1.96, 0) | E46: =ROUND($C$46 - (E44-$C$44)*1.552, 0)
A47: - Tỷ lệ suy giảm LNTT so kịch bản cơ sở | B47: 0 | C47: 0 | D47: =(D46-$C$46)/$C$46 | E47: =(E46-$C$46)/$C$46
A48: Vốn tự có (Tier 1 + Tier 2) | B48: =ROUND(B49*BCTC_MB_Goc!I62, 0) | C48: =ROUND($B$48 + C46*0.8*0.454, 0) | D48: =ROUND($B$48 + D46*0.8*0.454 - (D44-$C$44)*0.645, 0) | E48: =ROUND($B$48 + E46*0.8*0.454 - (E44-$C$44)*0.645, 0)
A49: Tổng tài sản có rủi ro (RWA) | B49: =ROUND(B37*0.9225, 0) | C49: =ROUND(C37*0.9225, 0) | D49: =ROUND(D37*0.9315, 0) | E49: =ROUND(E37*0.9315, 0)
A50: Tỷ lệ an toàn vốn (CAR stress theo TT 41) | B50: =BCTC_MB_Goc!I62 | C50: =C48/C49 | D50: =D48/D49 | E50: =E48/E49
A51: Thặng dư / (Thâm hụt) vốn so với ngưỡng 8,0% | B51: =B50-0.08 | C51: =C50-0.08 | D51: =D50-0.08 | E51: =E50-0.08
A53: BẢNG 4: KẾT LUẬN HỌC THUẬT VỀ ĐỘ NHẠY CỦA HAI MÔ HÌNH QUẢN TRỊ RỦI RO
A54: 1. Tính dễ bị tổn thương về vốn (Capital Vulnerability): | B54: Agribank xuất phát điểm CAR đạt 10,22% năm 2025 (BCTN 2025), nhưng do áp lực tăng RWA và trích lập bổ sung 26.500 tỷ đồng ở kịch bản Cực đoan, CAR lùi về 8,67% (thặng dư vốn chỉ còn +0,67% so với ngưỡng 8,0%).
A55: 2. Độ nhạy cảm lợi nhuận và danh mục rủi ro cao (Profit & Credit Sensitivity): | B55: MB chịu áp lực trích lập dự phòng bổ sung lớn hơn rất nhiều (lên tới 22.400 tỷ đồng ở kịch bản Cực đoan, bào mòn gần 70% LNTT) do tỷ trọng BĐS, TPDN và vay tín chấp tiêu dùng MCredit có độ nhạy rất cao với lãi suất.
A56: 3. Hàm ý đối với quản trị rủi ro cấp ngân hàng: | B56: Agribank cần tối ưu hóa RWA và giữ lại lợi nhuận để tăng vốn Tier 1; MB cần siết chặt hạn mức tập trung danh mục BĐS và áp dụng chính sách định giá bù đắp rủi ro tín chấp.
A58: 4. Hạn chế mô hình (soát xét 28/10/2026):
A59: (a) Các hệ số truyền dẫn cố định trong công thức (0,4685; 0,659; 0,98 – dự phòng; 0,657; 1,39; 1,333; 1,90; 1,96; 1,552 – LNTT; 1,72; 1,625; 0,645 – vốn tự có) là hệ số hiệu chỉnh do nhóm đặt, chưa được ước lượng thống kê.
A60: (b) Chi phí dự phòng tăng thêm vừa làm giảm LNTT (qua lợi nhuận giữ lại) vừa bị khấu trừ trực tiếp vào vốn tự có (dòng 29, 48) → mức giảm CAR ở kịch bản tiêu cực/cực đoan có xu hướng bị ước tính cao (thận trọng).
A61: (c) Kênh giảm giá BĐS (dòng 8) chỉ đi vào nhu cầu dự phòng của Agribank (dòng 25); công thức MB (dòng 44) chưa có kênh này. Kết quả dùng để so sánh độ nhạy tương đối, không phải dự báo.

Sheet IFRS9_Simulation
A1: MÔ PHỎNG TÁC ĐỘNG CHUYỂN ĐỔI CHUẨN MỰC IFRS 9 (EXPECTED CREDIT LOSS - ECL)
A2: Ước tính khoảng cách dự phòng (Provisioning Gap) giữa VAS (Thông tư 11/2021) và Chuẩn mực Quốc tế IFRS 9
A4: BẢNG 1: SO SÁNH PHƯƠNG PHÁP TRÍCH LẬP DỰ PHÒNG: VAS (TT 11) VS IFRS 9
A5: Giai đoạn tín dụng | B5: VAS / Thông tư 11/2021 (Incurred Loss) | C5: IFRS 9 Framework | D5: Công thức tính ECL | E5: Agribank Giả định (PD / LGD) | F5: MB Giả định (PD / LGD)
A6: Stage 1 (Performing) | B6: Nợ nhóm 1 (DP chung 0,75%) | C6: Không có SICR | D6: EAD x PD(12m) x LGD | E6: PD=1,2% | LGD=35% | F6: PD=1,5% | LGD=45%
A7: Stage 2 (Underperforming) | B7: Nợ nhóm 2 (DP cụ thể 5% sau TSBĐ) + TT 02 | C7: Gia tăng RRTD đáng kể (SICR) | D7: EAD x PD(Lifetime) x LGD | E7: PD=22,0% | LGD=45% (SICR: Nhóm 2 + Cơ cấu + 5% Nhóm 1) | F7: PD=28,0% | LGD=50% (SICR: Nhóm 2 + 6% Nhóm 1 + 30% TPDN)
A8: Stage 3 (Credit-impaired) | B8: Nợ nhóm 3-5 (DP cụ thể 20%, 50%, 100%) | C8: Nợ xấu / Suy giảm giá trị | D8: EAD x 100% x LGD | E8: PD=100% | LGD=85% (Chiết khấu EIR thời gian thu hồi TSBĐ) | F8: PD=100% | LGD=65% (Chiết khấu dòng tiền & nợ tín chấp)
A11: BẢNG 2: KẾT QUẢ ĐỊNH LƯỢNG MÔ PHỎNG IFRS 9 NĂM 2025 (Tỷ đồng)
A12: Khoản mục phân tích | B12: Dư nợ EAD Agribank | C12: ECL ước tính Agribank | D12: Dư nợ EAD MB | E12: ECL ước tính MB | F12: Phương pháp & Ghi chú
A13: Stage 1: Nợ đủ tiêu chuẩn (Nhóm 1) | B13: =0.95*(BCTC_Agribank_Goc!I17+BCTC_Agribank_Goc!I23) | C13: =B13*0.012*0.35 | D13: =0.94*BCTC_MB_Goc!I17 | E13: =D13*0.015*0.45 | F13: EAD x PD(12m) x LGD
A14: Stage 2: Nợ có SICR (Nhóm 2 + Nợ cơ cấu) | B14: =BCTC_Agribank_Goc!I18+0.05*(BCTC_Agribank_Goc!I17+BCTC_Agribank_Goc!I23) | C14: =B14*0.22*0.45 | D14: =BCTC_MB_Goc!I18+0.06*BCTC_MB_Goc!I17+0.3*BCTC_MB_Goc!I52 | E14: =D14*0.28*0.5 | F14: EAD x PD(Lifetime) x LGD
A15: Stage 3: Nợ xấu (Nhóm 3–5) | B15: =BCTC_Agribank_Goc!I25 | C15: =B15*1*0.85 | D15: =BCTC_MB_Goc!I23 | E15: =D15*1*0.65 | F15: EAD x 100% x LGD
A16: TỔNG DỰ PHÒNG ECL THEO IFRS 9 (A) | B16: =SUM(B13:B15) | C16: =SUM(C13:C15) | D16: =SUM(D13:D15) | E16: =SUM(E13:E15) | F16: Tổng dự phòng 3 giai đoạn
A17: TỔNG DỰ PHÒNG THEO VAS/TT11 HIỆN TẠI (B) | B17: =BCTC_Agribank_Goc!I24 | C17: =BCTC_Agribank_Goc!I33 | D17: =BCTC_MB_Goc!I22 | E17: =BCTC_MB_Goc!I33 | F17: Số dư quỹ dự phòng BCTC 2025
A18: CHÊNH LỆCH DỰ PHÒNG CẦN BỔ SUNG (GAP = A - B) | B18: 0 | C18: =C16-C17 | D18: 0 | E18: =E16-E17 | F18: Khoảng cách dự phòng trích thiếu
A19: Tỷ lệ thiếu hụt so với dự phòng hiện hành (%) | B19: 0 | C19: =C18/C17 | D19: 0 | E19: =E18/E17 | F19: Gap / Dự phòng hiện hành
A20: Vốn chủ sở hữu hiện hành (Equity 2025) | B20: 0 | C20: =BCTC_Agribank_Goc!I13 | D20: 0 | E20: =BCTC_MB_Goc!I15 | F20: Vốn CSH trên BCTC 2025
A21: Tác động khấu trừ vào Vốn CSH (sau thuế TNDN 20%) | B21: 0 | C21: =-C18*(1-0.2) | D21: 0 | E21: =-E18*(1-0.2) | F21: Gap x (1 - 20%)
A22: Tỷ lệ suy giảm Vốn chủ sở hữu (%) | B22: 0 | C22: =C21/C20 | D22: 0 | E22: =E21/E20 | F22: Khấu trừ / Vốn CSH
A23: Tỷ lệ CAR hiện hành theo Thông tư 41 (%) | B23: 0 | C23: =BCTC_Agribank_Goc!I58 | D23: 0 | E23: =BCTC_MB_Goc!I62 | F23: CAR công bố / ước tính 2025
A24: Tỷ lệ CAR sau khi áp dụng IFRS 9 (%) | B24: 0 | C24: =C23+(C21/B17) | D24: 0 | E24: =E23+(E21/D17) | F24: CAR sau khấu trừ vốn
A25: Mức suy giảm CAR (điểm phần trăm / bps) | B25: 0 | C25: =C24-C23 | D25: 0 | E25: =E24-E23 | F25: Chênh lệch điểm % CAR
A27: BẢNG 3: PHÂN TÍCH HỌC THUẬT VỀ TÁC ĐỘNG CHUYỂN ĐỔI IFRS 9
A28: 1. Cú sốc trích lập tại Stage 2: | B28: Dưới chuẩn IFRS 9, khi một khoản nợ bị xếp vào Stage 2 (SICR), ngân hàng phải trích lập dự phòng tổn thất trọn vòng đời (Lifetime ECL). Tại MB, tổng dự phòng ECL lên tới 27.157 tỷ đồng so với 13.151 tỷ đồng hiện trích theo VAS, tạo ra khoảng cách thiếu hụt 14.006 tỷ đồng (+106,5%).
A29: 2. Tác động bất đối xứng đến CAR: | B29: Agribank: LGD 35% (giai đoạn 1) và 45% (giai đoạn 2) nhờ TSBĐ là BĐS, nhưng 85% ở giai đoạn 3 vì thời gian xử lý TSBĐ kéo dài làm giá trị hiện tại của tiền thu hồi giảm. MB: 45%, 50%, 65%. Khoảng cách nhỏ của Agribank chủ yếu do đã giữ dự phòng cụ thể lớn; khoảng cách lớn của MB đến từ giai đoạn 2. CAR sau IFRS 9 dùng dư nợ cho vay thay RWA nên chỉ mang tính minh họa.
A30: 3. Hàm ý chiến lược: | B30: Việc áp dụng IFRS 9 sẽ là phép thử khắc nghiệt đối với chiến lược tăng trưởng nóng của các NHTMCP đa năng; ngân hàng nào có tỷ trọng cho vay tín chấp và TPDN cao sẽ phải đối mặt với áp lực tiêu hao vốn rất lớn.
A32: BẢNG 4: PHÂN TÍCH ĐỘ NHẠY (SENSITIVITY ANALYSIS) KHOẢNG CÁCH DỰ PHÒNG IFRS 9 & TỶ LỆ CAR NĂM 2025
A33: Kịch bản độ nhạy tham số (SICR Stage 2 & LGD) | B33: Agribank: Gap Dự phòng (Tỷ) | C33: Agribank: CAR sau IFRS 9 (%) | D33: MB: Gap Dự phòng (Tỷ) | E33: MB: CAR sau IFRS 9 (%) | F33: Diễn giải tác động độ nhạy
A34: 1. Kịch bản Cơ sở (Agribank SICR 5%, MB SICR 6%; LGD chuẩn) | B34: =C18 | C34: =C24 | D34: =E18 | E34: =E24 | F34: Kịch bản trung tâm trình bày tại Bảng 2
A35: 2. Tỷ lệ Nhóm 1 chuyển sang Stage 2 (SICR) thấp (= 3,0%) | B35: =(0.97*(BCTC_Agribank_Goc!I17+BCTC_Agribank_Goc!I23)*0.012*0.35 + (BCTC_Agribank_Goc!I18+0.03*(BCTC_Agribank_Goc!I17+BCTC_Agribank_Goc!I23))*0.22*0.45 + B15*0.85) - C17 | C35: =C23 - (B35*(1-0.2))/B17 | D35: =(0.97*BCTC_MB_Goc!I17*0.015*0.45 + (BCTC_MB_Goc!I18+0.03*BCTC_MB_Goc!I17+0.3*BCTC_MB_Goc!I52)*0.28*0.5 + D15*0.65) - E17 | E35: =E23 - (D35*(1-0.2))/D17 | F35: Khi chất lượng danh mục Nhóm 1 tốt (chỉ 3% bị SICR)
A36: 3. Tỷ lệ Nhóm 1 chuyển sang Stage 2 (SICR) trung bình (= 6,0%) | B36: =(0.94*(BCTC_Agribank_Goc!I17+BCTC_Agribank_Goc!I23)*0.012*0.35 + (BCTC_Agribank_Goc!I18+0.06*(BCTC_Agribank_Goc!I17+BCTC_Agribank_Goc!I23))*0.22*0.45 + B15*0.85) - C17 | C36: =C23 - (B36*(1-0.2))/B17 | D36: =(0.94*BCTC_MB_Goc!I17*0.015*0.45 + (BCTC_MB_Goc!I18+0.06*BCTC_MB_Goc!I17+0.3*BCTC_MB_Goc!I52)*0.28*0.5 + D15*0.65) - E17 | E36: =E23 - (D36*(1-0.2))/D17 | F36: Khi cả hai ngân hàng có cùng tỷ lệ 6% Nhóm 1 chuyển sang Stage 2
A37: 4. Tỷ lệ Nhóm 1 chuyển sang Stage 2 (SICR) cao (= 9,0%) | B37: =(0.91*(BCTC_Agribank_Goc!I17+BCTC_Agribank_Goc!I23)*0.012*0.35 + (BCTC_Agribank_Goc!I18+0.09*(BCTC_Agribank_Goc!I17+BCTC_Agribank_Goc!I23))*0.22*0.45 + B15*0.85) - C17 | C37: =C23 - (B37*(1-0.2))/B17 | D37: =(0.91*BCTC_MB_Goc!I17*0.015*0.45 + (BCTC_MB_Goc!I18+0.09*BCTC_MB_Goc!I17+0.3*BCTC_MB_Goc!I52)*0.28*0.5 + D15*0.65) - E17 | E37: =E23 - (D37*(1-0.2))/D17 | F37: Khi suy giảm kinh tế diện rộng làm 9% Nhóm 1 rơi vào Stage 2
A38: 5. Hệ số tổn thất LGD giảm 10 điểm % ở mọi giai đoạn (LGD -10%) | B38: =(B13*0.012*0.25 + B14*0.22*0.35 + B15*0.75) - C17 | C38: =C23 - MAX(0,B38)*(1-0.2)/B17 | D38: =(D13*0.015*0.35 + D14*0.28*0.4 + D15*0.55) - E17 | E38: =E23 - MAX(0,D38)*(1-0.2)/D17 | F38: Khi thanh khoản phát mại TSBĐ thuận lợi (Agribank dư dự phòng)
A39: 6. Hệ số tổn thất LGD tăng 10 điểm % ở mọi giai đoạn (LGD +10%) | B39: =(B13*0.012*0.45 + B14*0.22*0.55 + B15*0.95) - C17 | C39: =C23 - (B39*(1-0.2))/B17 | D39: =(D13*0.015*0.55 + D14*0.28*0.6 + D15*0.75) - E17 | E39: =E23 - (D39*(1-0.2))/D17 | F39: Khi thị trường BĐS đóng băng làm LGD tăng thêm 10 điểm %
A41: Lưu ý phương pháp (soát xét 28/10/2026):
A42: (a) EAD Stage 2 của MB gồm 30% TPDN do TCKT phát hành (0,30 × 23.410 tỷ; ECL ≈ 983 tỷ), trong khi dự phòng VAS so sánh (E17 = 13.151 tỷ) chỉ là dự phòng cho vay khách hàng → Gap 14.006 tỷ gồm cả phần TPDN.
A43: (b) CAR sau IFRS 9 (dòng 24, 34–39) = CAR hiện hành − tác động sau thuế / dư nợ cho vay (B17, D17), dùng dư nợ thay cho RWA → mức giảm (bps) mang tính minh họa.
A44: (c) Phân bổ dự phòng VAS theo Stage trong Bảng 11 (Word): Stage 1 = dự phòng chung; Stage 2 = 5% × nợ nhóm 2; Stage 3 = dự phòng cụ thể còn lại.

Sheet BCTC_Agribank_Goc
A1: BẢNG DỮ LIỆU GỐC TRÍCH XUẤT BCTC KIỂM TOÁN & BCTN AGRIBANK (2020–2025)
A2: Đơn vị: Tỷ đồng (Quy đổi chính xác từ Triệu VND trên BCTC Kiểm toán). Liên kết tự động sang sheet Du_lieu, Chi_tieu, Stress_Testing, IFRS9_Simulation.
A4: Mã TM | B4: Chỉ tiêu Báo cáo Tài chính & Thuyết minh Kiểm toán | C4: Đơn vị | D4: 2020 | E4: 2021 | F4: 2022 | G4: 2023 | H4: 2024 | I4: 2025 | J4: Trích dẫn File PDF gốc, Thuyết minh & Trang
A5: I | B5: BẢNG CÂN ĐỐI KẾ TOÁN & NGOÀI BẢNG (HỢP NHẤT & RIÊNG LẺ)
A6: B02-HN | B6: Tổng tài sản (Hợp nhất) | C6: tỷ | D6: 1568126.9 | E6: 1695932.7 | F6: 1874839.2 | G6: 2044927.4 | H6: 2234854.2 | I6: 2686597.8 | J6: BCTC HN 2020 (tr.7), 2021 (tr.6), 2023 (tr.20), 2025 (tr.126)
A7: B02-RL | B7: Tổng tài sản (Riêng lẻ - Ngân hàng mẹ) | C7: tỷ | D7: 1566966.9 | E7: 1694231.5 | F7: 1873684.6 | G7: 2042976.2 | H7: 2231961.6 | I7: 2682737.8 | J7: BCTC Riêng 2021 (tr.6), 2023 (tr.132), 2025 (tr.6)
A8: TM 9/10 | B8: Cho vay khách hàng gộp (Hợp nhất) | C8: tỷ | D8: =D24 | E8: =E24 | F8: =F24 | G8: =G24 | H8: =H24 | I8: =I24 | J8: TM 9 BCTC HN 2020 (tr.35), TM 10 2021 (tr.45), TM 9 2023 (tr.61), TM 9 2025 (tr.170)
A9: TM 9/10 | B9: Cho vay khách hàng gộp (Riêng lẻ - Ngân hàng mẹ) | C9: tỷ | D9: =D22 | E9: =E22 | F9: =F22 | G9: =G22 | H9: =H22 | I9: =I22 | J9: TM 10 BCTC Riêng 2021 (tr.38), TM 9 2023 (tr.166), TM 9 2025 (tr.72)
A10: TM 10/11 | B10: Dự phòng rủi ro cho vay khách hàng (Hợp nhất) | C10: tỷ | D10: =D33 | E10: =E33 | F10: =F33 | G10: =G33 | H10: =H33 | I10: =I33 | J10: TM 10 BCTC HN 2020 (tr.37), TM 11 2021 (tr.48), TM 10 2023 (tr.64), TM 10 2025 (tr.172)
A11: TM 10/11 | B11: Dự phòng rủi ro cho vay khách hàng (Riêng lẻ) | C11: tỷ | D11: 23877.048 | E11: 34023.924 | F11: 36276.157 | G11: 37487.862 | H11: 37770.426 | I11: 36976.803 | J11: TM 11 BCTC Riêng 2021 (tr.41), TM 10 2023 (tr.169), TM 10 2025 (tr.74)
A12: TM 18/19 | B12: Tiền gửi của khách hàng (Hợp nhất) | C12: tỷ | D12: 1404875.8 | E12: 1542504.4 | F12: 1623935.1 | G12: 1817271 | H12: 1914664.4 | I12: 2156382.7 | J12: B02/TCTD-HN 2020-2025
A13: TM 23/24 | B13: Tổng Vốn chủ sở hữu (Hợp nhất) | C13: tỷ | D13: 73084.295 | E13: 76087.34 | F13: 86997.553 | G13: 100535.85 | H13: 124067.76 | I13: 131191.25 | J13: B02/TCTD-HN 2020-2025
A14: TM 23/24 | B14: Trong đó: Vốn điều lệ | C14: tỷ | D14: 30709.923 | E14: 34328.393 | F14: 34446.863 | G14: 41268.833 | H14: 51638.603 | I14: 51638.603 | J14: B02/TCTD-HN 2020-2025
A15: TM 39/40 | B15: Ngoài bảng: Nợ khó đòi đã xử lý đang theo dõi (Hợp nhất) | C15: tỷ | D15: 145000 | E15: 156800 | F15: 181111.74 | G15: 205217.79 | H15: 235401.95 | I15: 278372.38 | J15: TM 39 BCTC HN 2023 (tr.93), TM 40 BCTC HN 2025 (tr.198); 2020-21 ước tính ngược từ dòng xóa nợ
A16: II | B16: PHÂN TÍCH CHẤT LƯỢNG NỢ CHO VAY (THUYẾT MINH 9 / 10)
A17: TM 9.1 | B17: Nhóm 1 - Nợ đủ tiêu chuẩn | C17: tỷ | D17: 1161020 | E17: 1261194.3 | F17: 1381920 | G17: 1489187.1 | H17: 1662997.8 | I17: 1926570.3 | J17: TM 9 BCTC HN 2020 (tr.35), TM 10 2021 (tr.45), TM 9 2023 (tr.61), TM 9 2025 (tr.170)
A18: TM 9.1 | B18: Nhóm 2 - Nợ cần chú ý | C18: tỷ | D18: 30077.806 | E18: 28446.282 | F18: 35279.613 | G18: 32339.641 | H18: 29202.409 | I18: 21282.062 | J18: TM 9 BCTC HN 2020 (tr.35), TM 10 2021 (tr.45), TM 9 2023 (tr.61), TM 9 2025 (tr.170)
A19: TM 9.1 | B19: Nhóm 3 - Nợ dưới tiêu chuẩn | C19: tỷ | D19: 2744.748 | E19: 3141.256 | F19: 3887.707 | G19: 3880.436 | H19: 2282.808 | I19: 3325.667 | J19: TM 9 BCTC HN 2020 (tr.35), TM 10 2021 (tr.45), TM 9 2023 (tr.61), TM 9 2025 (tr.170)
A20: TM 9.1 | B20: Nhóm 4 - Nợ nghi ngờ | C20: tỷ | D20: 2425.499 | E20: 3379.431 | F20: 3176.562 | G20: 5592.596 | H20: 4088.234 | I20: 2064.309 | J20: TM 9 BCTC HN 2020 (tr.35), TM 10 2021 (tr.45), TM 9 2023 (tr.61), TM 9 2025 (tr.170)
A21: TM 9.1 | B21: Nhóm 5 - Nợ có khả năng mất vốn | C21: tỷ | D21: 16356.701 | E21: 18033.338 | F21: 19000.009 | G21: 19247.538 | H21: 22637.559 | I21: 20220.426 | J21: TM 9 BCTC HN 2020 (tr.35), TM 10 2021 (tr.45), TM 9 2023 (tr.61), TM 9 2025 (tr.170)
A22: TM 9.1 | B22: Cộng Dư nợ Ngân hàng mẹ (Riêng lẻ = Nhóm 1..5) | C22: tỷ | D22: =SUM(D17:D21) | E22: =SUM(E17:E21) | F22: =SUM(F17:F21) | G22: =SUM(G17:G21) | H22: =SUM(H17:H21) | I22: =SUM(I17:I21) | J22: Tổng cộng dư nợ phân loại Nhóm 1-5 tại Ngân hàng mẹ
A23: TM 9.1 | B23: Dư nợ cho vay và CTTC của công ty con (ALC I, ALC II) với KH ngoài | C23: tỷ | D23: 1333.532 | E23: 2254.325 | F23: 1537.837 | G23: 1910.526 | H23: 2173.422 | I23: 2906.02 | J23: TM 9 BCTC HN 2020 (tr.35), TM 10 2021 (tr.45), TM 9 2023 (tr.61), TM 9 2025 (tr.170)
A24: TM 9.1 | B24: Tổng Dư nợ cho vay khách hàng Hợp nhất | C24: tỷ | D24: =D22+D23 | E24: =E22+E23 | F24: =F22+F23 | G24: =G22+G23 | H24: =H22+H23 | I24: =I22+I23 | J24: Khớp 100% chỉ tiêu VI.1 trên Bảng cân đối kế toán Hợp nhất
A25: TM 9.1 | B25: Tổng Nợ xấu nội bảng (Nhóm 3 + Nhóm 4 + Nhóm 5) | C25: tỷ | D25: =SUM(D19:D21) | E25: =SUM(E19:E21) | F25: =SUM(F19:F21) | G25: =SUM(G19:G21) | H25: =SUM(H19:H21) | I25: =SUM(I19:I21) | J25: Tổng nợ xấu Nhóm 3-5 theo Thuyết minh BCTC kiểm toán
A26: Tỷ lệ | B26: Tỷ lệ NPL tính từ BCTC Hợp nhất (= Nợ xấu / Dư nợ HN) | C26: % | D26: =D25/D24 | E26: =E25/E24 | F26: =F25/F24 | G26: =G25/G24 | H26: =H25/H24 | I26: =I25/I24 | J26: Tỷ lệ nợ xấu tính trực tiếp trên Dư nợ cho vay KH Hợp nhất
A27: Tỷ lệ | B27: Tỷ lệ NPL tính từ BCTC Riêng lẻ (= Nợ xấu / Dư nợ Riêng) | C27: % | D27: =D25/D22 | E27: =E25/E22 | F27: =F25/F22 | G27: =G25/G22 | H27: =H25/H22 | I27: =I25/I22 | J27: Tỷ lệ nợ xấu tính trực tiếp trên Dư nợ cho vay KH Ngân hàng mẹ
A28: BCTN | B28: Tỷ lệ NPL nội bảng chuẩn TT11/TT31 (Bảng chỉ tiêu BCTN 2024-2025) | C28: % | D28: 0.0163 | E28: 0.0178 | F28: 0.0171 | G28: 0.0177 | H28: 0.0158 | I28: 0.0117 | J28: BCTN 2024 (tr.16 PDF) & BCTN 2025 (tr.21 PDF) - tính trên tổng cấp TD nội bảng
A29: BCTN | B29: Tỷ lệ NPL theo Báo cáo điều hành từng năm (BCTN 2020-2025) | C29: % | D29: 0.0164 | E29: 0.0171 | F29: 0.0164 | G29: 0.0165 | H29: 0.0156 | I29: 0.0114 | J29: BCTN 2020 (tr.18), 2021 (tr.34), 2022 (tr.38), 2023 (tr.39), 2024 (tr.10), 2025 (tr.4)
A30: III | B30: BIẾN ĐỘNG DỰ PHÒNG RỦI RO CHO VAY KHÁCH HÀNG HỢP NHẤT (TM 10 / 11)
A31: TM 10/11 | B31: Số dư Dự phòng chung cuối năm (Hợp nhất) | C31: tỷ | D31: 8856.752 | E31: 9743.324 | F31: 10598.299 | G31: 11412.795 | H31: 12628.766 | I31: 14602.264 | J31: TM 10 BCTC HN 2020 (tr.37), TM 11 2021 (tr.48), TM 10 2023 (tr.64), TM 10 2025 (tr.172)
A32: TM 10/11 | B32: Số dư Dự phòng cụ thể cuối năm (Hợp nhất) | C32: tỷ | D32: 15600.737 | E32: 24840.15 | F32: 26237.403 | G32: 26600.362 | H32: 25649.989 | I32: 22862.985 | J32: TM 10 BCTC HN 2020 (tr.37), TM 11 2021 (tr.48), TM 10 2023 (tr.64), TM 10 2025 (tr.173)
A33: TM 10/11 | B33: Tổng số dư Dự phòng rủi ro cho vay KH cuối năm (Hợp nhất) | C33: tỷ | D33: =D31+D32 | E33: =E31+E32 | F33: =F31+F32 | G33: =G31+G32 | H33: =H31+H32 | I33: =I31+I32 | J33: Tổng quỹ dự phòng rủi ro cho vay khách hàng = DP chung + DP cụ thể
A34: TM 10/11 | B34: Tổng trích lập dự phòng cho vay KH trong năm (Hợp nhất) | C34: tỷ | D34: 18732.286 | E34: 22047.625 | F34: 27171.919 | G34: 19347.073 | H34: 26658.287 | I34: 31807.972 | J34: TM 10/11 BCTC HN (Trích lập DP chung + Trích lập DP cụ thể trong năm)
A35: TM 10/11 | B35: Sử dụng dự phòng để xử lý rủi ro trong năm (Nợ xóa - Hợp nhất) | C35: tỷ | D35: 14125.505 | E35: 11921.64 | F35: 24547.581 | G35: 18169.618 | H35: 26444.41 | I35: 32621.478 | J35: TM 10 BCTC HN 2020 (tr.37), TM 11 2021 (tr.48), TM 10 2023 (tr.64), TM 10 2025 (tr.173)
A36: Tỷ lệ | B36: Tỷ lệ bao phủ nợ xấu Hợp nhất (LLCR = Tổng DPRR HN / Nợ xấu) | C36: % | D36: =D33/D25 | E36: =E33/E25 | F36: =F33/F25 | G36: =G33/G25 | H36: =H33/H25 | I36: =I33/I25 | J36: LLCR Hợp nhất tính trực tiếp từ BCTC Kiểm toán
A37: Tỷ lệ | B37: Tỷ lệ bao phủ nợ xấu Riêng lẻ (LLCR = Tổng DPRR Riêng / Nợ xấu) | C37: % | D37: =D11/D25 | E37: =E11/E25 | F37: =F11/F25 | G37: =G11/G25 | H37: =H11/H25 | I37: =I11/I25 | J37: LLCR Ngân hàng mẹ tính trực tiếp từ BCTC Kiểm toán Riêng lẻ
A38: IV | B38: BÁO CÁO KẾT QUẢ HOẠT ĐỘNG KINH DOANH HỢP NHẤT & THU NỢ XLRR
A39: B03-HN | B39: Thu nhập lãi thuần (NII - Hợp nhất) | C39: tỷ | D39: 43660.623 | E39: 47041.165 | F39: 60189.542 | G39: 55964.737 | H39: 66554.116 | I39: 70616.6 | J39: B03/TCTD-HN: 2020 (tr.10), 2021 (tr.10), 2023 (tr.24), 2025 (tr.130)
A40: TM 29/30 | B40: Lãi thuần từ hoạt động khác (Mục VI KQKD Hợp nhất) | C40: tỷ | D40: 8107.448 | E40: 8257.912 | F40: 9842.212 | G40: 10529.197 | H40: 10453.924 | I40: 16182.827 | J40: TM 30 BCTC HN 2020 (tr.58), 2021 (tr.65), TM 29 2023 (tr.86), TM 30 2025 (tr.193)
A41: TM 29/30 | B41: Trong đó: Thu từ các khoản nợ đã xử lý rủi ro (TM 29/30 BCTC) | C41: tỷ | D41: 8673.418 | E41: 8810.266 | F41: 10267.203 | G41: 11167.15 | H41: 8412.708 | I41: 12122.774 | J41: TM 30 BCTC HN 2020 (tr.58), 2021 (tr.65), TM 29 2023 (tr.86), TM 30 2025 (tr.193)
A42: BCTN | B42: Tổng thu nợ sau xử lý rủi ro công bố tại BCTN (gồm thu xử lý TS) | C42: tỷ | D42: 8673.418 | E42: 8810.266 | F42: 10267.203 | G42: 11167.15 | H42: 11662 | I42: 16305 | J42: BCTN 2024 (tr.27 PDF: 11.662 tỷ) & BCTN 2025 (tr.4 PDF: 16.305 tỷ)
A43: B03-HN | B43: Tổng thu nhập hoạt động (TOI - Hợp nhất) | C43: tỷ | D43: 58052.435 | E43: 62106.224 | F43: 77860.561 | G43: 76138.662 | H43: 86496.47 | I43: 97521.784 | J43: B03/TCTD-HN 2020-2025
A44: TM 32/33 | B44: Tổng chi phí hoạt động (OPEX - Hợp nhất) | C44: tỷ | D44: 26117.208 | E44: 24801.001 | F44: 28150.016 | G44: 30932.407 | H44: 32263.408 | I44: 34543.97 | J44: B03/TCTD-HN 2020-2025
A45: B03-HN | B45: Lợi nhuận thuần từ HĐKD trước CP DPRR (PPOP - Hợp nhất) | C45: tỷ | D45: =D43-D44 | E45: =E43-E44 | F45: =F43-F44 | G45: =G43-G44 | H45: =H43-H44 | I45: =I43-I44 | J45: TOI trừ OPEX trên B03/TCTD-HN
A46: B03-HN | B46: Chi phí dự phòng rủi ro tín dụng trên KQKD (Hợp nhất) | C46: tỷ | D46: 18732.286 | E46: 22047.625 | F46: 27171.92 | G46: 19347.073 | H46: 26658.287 | I46: 31808.213 | J46: B03/TCTD-HN 2020-2025 (Ghi chú: BCTN 2025 sau ĐC KTNN năm 2021 là 21.676, năm 2023 là 19.399)
A47: B03-HN | B47: Tổng lợi nhuận trước thuế (LNTT - Hợp nhất) | C47: tỷ | D47: =D45-D46 | E47: =E45-E46 | F47: =F45-F46 | G47: =G45-G46 | H47: =H45-H46 | I47: =I45-I46 | J47: B03/TCTD-HN 2020-2025 (BCTN 2025 sau ĐC KTNN: 2020=12.869, 2021=15.339, 2023=25.641)
A48: B03-HN | B48: Lợi nhuận sau thuế (LNST - Hợp nhất) | C48: tỷ | D48: 10516.804 | E48: 12261.032 | F48: 18043 | G48: 20695.801 | H48: 22067.275 | I48: 24954.573 | J48: B03/TCTD-HN 2020-2025
A49: V | B49: TÀI SẢN ĐẢM BẢO, DƯ NỢ THEO NGÀNH, CAR & NỢ CƠ CẤU
A50: TM 36/37 | B50: Tổng giá trị Tài sản bảo đảm của khách hàng (Hợp nhất) | C50: tỷ | D50: 2036527.6 | E50: 2284953.3 | F50: 2530274.6 | G50: 2927711.3 | H50: 3189972.2 | I50: 3739943.1 | J50: TM 37 BCTC HN 2020 (tr.62), 2021 (tr.69), TM 36 2023 (tr.91), TM 37 2025 (tr.196)
A51: TM 36/37 | B51: Tổng tài sản, GTCG nhận thế chấp cầm cố (gồm cả TCTD khác) | C51: tỷ | D51: 2064379.6 | E51: 2327020.3 | F51: 2545250.4 | G51: 2946331.8 | H51: 3196264 | I51: 3794977.6 | J51: TM 37 BCTC HN 2020 (tr.62), 2021 (tr.69), TM 36 2023 (tr.91), TM 37 2025 (tr.196)
A52: TM 36/37 | B52: Trong đó: Bất động sản thế chấp của khách hàng | C52: tỷ | D52: 1840466.7 | E52: 2018025.7 | F52: 2289606.1 | G52: 2645514.4 | H52: 2923973.1 | I52: 3371568.3 | J52: TM 37 BCTC HN 2020 (tr.62), 2021 (tr.69), TM 36 2023 (tr.91), TM 37 2025 (tr.196)
A53: TM 9(iii) | B53: Dư nợ ngành Nông nghiệp, lâm nghiệp và thủy sản | C53: tỷ | D53: 323629.75 | E53: 339749.58 | F53: 370719.69 | G53: 400433.01 | H53: 437858.83 | I53: 506222.91 | J53: TM 9.3/10(iii) BCTC HN 2020-2025 (chiếm 25,4% - 26,7% dư nợ)
A54: TM 9(iii) | B54: Dư nợ ngành Kinh doanh Bất động sản | C54: tỷ | D54: 16338.338 | E54: 17908.762 | F54: 17417.818 | G54: 20962.953 | H54: 30944.741 | I54: 46864.047 | J54: TM 9.3/10(iii) BCTC HN 2020-2025 (chiếm 1,21% - 2,37% dư nợ)
A55: TM 9(iii) | B55: Dư nợ ngành Xây dựng | C55: tỷ | D55: 74069.668 | E55: 78205.238 | F55: 82854.414 | G55: 85002.858 | H55: 85840.224 | I55: 87733.677 | J55: TM 9.3/10(iii) BCTC HN 2020-2025 (chiếm 4,44% - 6,10% dư nợ)
A56: TM 9(iv) | B56: Dư nợ Cho vay cá nhân và hộ gia đình | C56: tỷ | D56: 838618.21 | E56: 910324.56 | F56: 1031470.5 | G56: 1127715.4 | H56: 1271822.2 | I56: 1477695.5 | J56: TM 9.4/10(iv) BCTC HN 2020-2025 (chiếm 69,1% - 74,8% dư nợ)
A57: BCTN | B57: Tỷ trọng dư nợ Nông nghiệp - Nông thôn ('Tam nông') / Dư nợ nền KT | C57: % | D57: ~70% | E57: 65–70% | F57: >65% | G57: 0.627 | H57: 0.617 | I57: 0.641 | J57: BCTN 2020–2022 công bố khoảng (~70%, 65-70%, >65%); BCTN 2023–2025 công bố chính xác: 62,7%; 61,7%; 64,1%
A58: BCTN | B58: Hệ số CAR công bố tại BCTN (2020–2022: TT 22/2019; 2023–2025: TT 41/2016) | C58: % | D58: 0.1058 | E58: 0.105 | F58: 0.108 | G58: 0.092 | H58: 0.1136 | I58: 0.1022 | J58: BCTN 2024 (tr.16 PDF) & BCTN 2025 (tr.21 PDF)
A59: BCTN | B59: Hệ số CAR riêng lẻ từng năm (2020–2022: TT 22/2019; từ 2023: TT 41/2016) | C59: % | D59: 0.103 | E59: 0.102 | F59: 0.106 | G59: 0.0915 | H59: 0.1135 | I59: 0.1022 | J59: BCTN 2020 (10,3%), 2021 (10,2%), 2022 (10,6%), 2023 (>9,0% / 9,15%), 2024 (11,35%), 2025 (10,22%)
A60: BCTN | B60: Dư nợ cơ cấu giữ nguyên nhóm nợ theo TT 02/2023 (xác nhận tại BCTN 2023) | C60: tỷ | D60: 0 | E60: 0 | F60: 0 | G60: 37876 | H60: 0 | I60: 0 | J60: BCTN 2023 (tr.39): 37.876 tỷ / 4.249 KH; cuối 2024 hết hạn TT02 (trích đủ 100% DP); 2025 cơ cấu TT53 Yagi không công bố số dư
A61: BCTN | B61: Dư nợ cơ cấu giữ nguyên nhóm nợ theo TT 01/2020, 03/2021, 14/2021 | C61: tỷ | D61: 33700 | E61: 21400 | F61: 0 | G61: 0 | H61: 0 | I61: 0 | J61: BCTN 2021 (tr.41): cơ cấu cho gần 17.000 KH (không công bố số dư tuyệt đối); chấm dứt sau 30/6/2022 (BCTN 2022 tr.8)
A62: B02-HN | B62: Dư nợ cho vay khách hàng gộp năm 2019 (TM 9 BCTC HN 2020 Deloitte) | C62: tỷ | D62: 1123403.4 | J62: TM 9 BCTC HN 2020 kiểm toán Deloitte (tr.7, Mẫu B02/TCTD-HN cột 31/12/2019: 1.123.403.404 triệu VND)
A63: TM 9.2 | B63: Nợ xấu nhóm 3–5 hợp nhất năm 2019 (TM 9.2 BCTC HN 2020 Deloitte) | C63: tỷ | D63: 17845.879 | J63: TM 9.2 BCTC HN 2020 kiểm toán Deloitte (tr.36: N3=3.371,274 tỷ; N4=1.976,000 tỷ; N5=12.498,605 tỷ; NPL=1,59%)
A64: TM 9.2 | B64: Nợ cần chú ý (Nhóm 2) năm 2019 (TM 9.2 BCTC HN 2020 Deloitte) | C64: tỷ | D64: 34162.62 | J64: TM 9.2 BCTC HN 2020 kiểm toán Deloitte (tr.36: Nợ nhóm 2 chiếm 3,05% tổng dư nợ cho vay)
A65: TM 10 | B65: Tổng số dư dự phòng rủi ro cho vay khách hàng năm 2019 (TM 10 BCTC 2020) | C65: tỷ | D65: 19850.708 | J65: TM 10 BCTC HN 2020 kiểm toán Deloitte (tr.35: DPCU=11.725,821 tỷ; DPCH=8.124,887 tỷ; LLCR 2019 = 111,2%)
A66: TM 30 | B66: Thu từ các khoản nợ đã xử lý rủi ro năm 2019 (TM 30 BCTC HN 2020 Deloitte) | C66: tỷ | D66: 11535.327 | J66: TM 30 BCTC HN 2020 kiểm toán Deloitte (tr.58: Thu nợ gốc=9.525,849 tỷ; Thu lãi=2.009,478 tỷ)
A67: B03-HN | B67: Chi phí dự phòng rủi ro tín dụng năm 2019 (Báo cáo KQKD HN 2020 Deloitte) | C67: tỷ | D67: 20643.405 | J67: Mẫu B03/TCTD-HN Báo cáo KQKD HN 2020 kiểm toán Deloitte (tr.10, cột năm trước: 20.643.405 triệu VND)
A68: B03-HN | B68: Tổng lợi nhuận trước thuế năm 2019 (Báo cáo KQKD HN 2020 Deloitte) | C68: tỷ | D68: 13933.949 | J68: Mẫu B03/TCTD-HN Báo cáo KQKD HN 2020 kiểm toán Deloitte (tr.10, cột năm trước: 13.933.949 triệu VND)

Sheet BCTC_MB_Goc
A1: BẢNG DỮ LIỆU GỐC TRÍCH XUẤT BCTC KIỂM TOÁN & BCTN MBBANK (2020–2025)
A2: Đơn vị: Tỷ đồng (Quy đổi chính xác từ Triệu VND trên BCTC Kiểm toán). Liên kết tự động sang sheet Du_lieu, Chi_tieu, Stress_Testing, IFRS9_Simulation.
A4: Mã TM | B4: Chỉ tiêu Báo cáo Tài chính & Thuyết minh Kiểm toán | C4: Đơn vị | D4: 2020 | E4: 2021 | F4: 2022 | G4: 2023 | H4: 2024 | I4: 2025 | J4: Trích dẫn File PDF gốc, Thuyết minh & Trang
A5: I | B5: BẢNG CÂN ĐỐI KẾ TOÁN (HỢP NHẤT & RIÊNG LẺ)
A6: B02-HN | B6: Tổng tài sản Có (Hợp nhất) | C6: tỷ | D6: 494982.16 | E6: 607140.42 | F6: 728532.37 | G6: 944953.64 | H6: 1128801.1 | I6: 1615763.9 | J6: B02/TCTD-HN: BCTN 2020 (tr.129), 2021 (tr.177), 2022 (tr.197), BCTC HN 2024 (tr.6), BCTN 2025 (tr.279)
A7: B02-RL | B7: Tổng tài sản Có (Riêng lẻ - Ngân hàng mẹ) | C7: tỷ | D7: 477839.59 | E7: 577009.65 | F7: 690664.58 | G7: 902044.95 | H7: 1067158.3 | I7: 1528579.2 | J7: B02/TCTD Riêng lẻ: BCTC Riêng 2021 (tr.6), 2022 (tr.6), 2024 (tr.6), 2025 (tr.6)
A8: TM 10/9 | B8: Cho vay khách hàng gộp (Hợp nhất) | C8: tỷ | D8: =D22 | E8: =E22 | F8: =F22 | G8: =G22 | H8: =H22 | I8: =I22 | J8: TM 10 BCTC HN 2020-2024, TM 9 BCTC HN 2025
A9: TM 10/9 | B9: Cho vay khách hàng gộp (Riêng lẻ - Ngân hàng mẹ) | C9: tỷ | D9: =D28 | E9: =E28 | F9: =F28 | G9: =G28 | H9: =H28 | I9: =I28 | J9: TM 10 BCTC Riêng 2021-2024, TM 9 BCTC Riêng 2025
A10: TM 11/10 | B10: Dự phòng rủi ro cho vay khách hàng (Hợp nhất) | C10: tỷ | D10: =D33 | E10: =E33 | F10: =F33 | G10: =G33 | H10: =H33 | I10: =I33 | J10: TM 11 BCTC HN 2020-2024, TM 10 BCTC HN 2025
A11: TM 11/10 | B11: Dự phòng rủi ro cho vay khách hàng (Riêng lẻ) | C11: tỷ | D11: 4128.256 | E11: 8118.66 | F11: 10706.62 | G11: 9383.404 | H11: 9920.824 | I11: 11632.139 | J11: TM 11 BCTC Riêng 2021 (tr.33), 2022 (tr.35), 2024 (tr.39), TM 10 2025 (tr.34)
A12: TM 12/13 | B12: Chứng khoán đầu tư thuần (Hợp nhất) | C12: tỷ | D12: 99713.646 | E12: 128806.24 | F12: 159580.03 | G12: 147923.2 | H12: 209637.38 | I12: 225574.85 | J12: B02/TCTD-HN Mục VIII (AFS + HTM - Dự phòng CKĐT)
A13: TM 12/11 | B13: Hoạt động mua nợ thuần (Hợp nhất) | C13: tỷ | D13: 0 | E13: 1.766 | F13: 1006.733 | G13: 1789.868 | H13: 951.509 | I13: 2443.895 | J13: B02/TCTD-HN Mục VII
A14: TM 20 | B14: Tiền gửi của khách hàng (Hợp nhất) | C14: tỷ | D14: 310960.35 | E14: 384692.16 | F14: 443605.64 | G14: 567532.58 | H14: 714154.48 | I14: 921368.13 | J14: B02/TCTD-HN Mục III (Nợ phải trả)
A15: TM 25 | B15: Tổng Vốn chủ sở hữu (Hợp nhất) | C15: tỷ | D15: 50099.495 | E15: 62486.023 | F15: 79613.219 | G15: 96711.159 | H15: 117059.58 | I15: 142022.52 | J15: B02/TCTD-HN Mục VIII (Vốn và các quỹ)
A16: II | B16: PHÂN TÍCH CHẤT LƯỢNG NỢ CHO VAY HỢP NHẤT & RIÊNG LẺ (TM 10.1 / 9.1)
A17: TM 10.1 | B17: Nhóm 1 - Nợ đủ tiêu chuẩn (Hợp nhất, gồm cho vay ký quỹ MBS) | C17: tỷ | D17: 292627.5 | E17: 356373.79 | F17: 447734.26 | G17: 587326.31 | H17: 751875.63 | I17: 1059781.8 | J17: TM 10.1 BCTC HN 2020-2024 & TM 9.1 BCTC HN 2025 (Trong đó ký quỹ MBS: 4.123 -> 15.041 tỷ)
A18: TM 10.1 | B18: Nhóm 2 - Nợ cần chú ý (Hợp nhất) | C18: tỷ | D18: 2421.678 | E18: 3912.949 | F18: 7808.932 | G18: 13917.867 | H18: 12196.782 | I18: 10210.04 | J18: TM 10.1 BCTC HN 2020 (tr.159), 2021 (tr.209), 2022 (tr.234), 2024 (tr.38), TM 9.1 2025 (tr.311)
A19: TM 10.1 | B19: Nhóm 3 - Nợ dưới tiêu chuẩn (Hợp nhất) | C19: tỷ | D19: 889.758 | E19: 1433.433 | F19: 1517.212 | G19: 3210.741 | H19: 3379.646 | I19: 3276.216 | J19: TM 10.1 BCTC HN 2020-2024 & TM 9.1 BCTC HN 2025
A20: TM 10.1 | B20: Nhóm 4 - Nợ nghi ngờ (Hợp nhất) | C20: tỷ | D20: 973.564 | E20: 1015.111 | F20: 1220.77 | G20: 3704.226 | H20: 4599.274 | I20: 4330.016 | J20: TM 10.1 BCTC HN 2020-2024 & TM 9.1 BCTC HN 2025
A21: TM 10.1 | B21: Nhóm 5 - Nợ có khả năng mất vốn (Hợp nhất) | C21: tỷ | D21: 1384.484 | E21: 819.491 | F21: 2293.312 | G21: 2889.691 | H21: 4606.512 | I21: 6421.264 | J21: TM 10.1 BCTC HN 2020-2024 & TM 9.1 BCTC HN 2025
A22: TM 10.1 | B22: Tổng Dư nợ cho vay khách hàng Hợp nhất (= SUM Nhóm 1..5) | C22: tỷ | D22: =SUM(D17:D21) | E22: =SUM(E17:E21) | F22: =SUM(F17:F21) | G22: =SUM(G17:G21) | H22: =SUM(H17:H21) | I22: =SUM(I17:I21) | J22: Khớp 100% chỉ tiêu VI.1 trên Bảng cân đối kế toán Hợp nhất
A23: TM 10.1 | B23: Tổng Nợ xấu nội bảng Hợp nhất (Nhóm 3 + Nhóm 4 + Nhóm 5) | C23: tỷ | D23: =SUM(D19:D21) | E23: =SUM(E19:E21) | F23: =SUM(F19:F21) | G23: =G19+G20+G21 | H23: =SUM(H19:H21) | I23: =SUM(I19:I21) | J23: Tổng nợ xấu hợp nhất kiểm toán
A24: Tỷ lệ | B24: Tỷ lệ NPL Hợp nhất (= Nợ xấu HN / Dư nợ cho vay HN) | C24: % | D24: =D23/D22 | E24: =E23/E22 | F24: =F23/F22 | G24: =G23/G22 | H24: =H23/H22 | I24: =I23/I22 | J24: NPL hợp nhất (không gồm TPDN): 1,09% - 0,90% - 1,09% - 1,60% - 1,62% - 1,29%
A25: TM 10.1-RL | B25: Nhóm 1 - Nợ đủ tiêu chuẩn (Riêng lẻ - Ngân hàng mẹ) | C25: tỷ | D25: 279605.81 | E25: 336767.46 | F25: 426450.07 | G25: 561512.92 | H25: 717557.79 | I25: 1013857.4 | J25: TM 10.1 BCTC Riêng 2021 (tr.32), 2022 (tr.33), 2024 (tr.37), TM 9.1 2025 (tr.33)
A26: TM 10.1-RL | B26: Nhóm 2 - Nợ cần chú ý (Riêng lẻ - Ngân hàng mẹ) | C26: tỷ | D26: 1795.944 | E26: 2190.055 | F26: 5115.654 | G26: 8228.168 | H26: 6542.954 | I26: 5728.344 | J26: TM 10.1 BCTC Riêng 2021-2024 & TM 9.1 2025 (Năm 2024 sau ĐC KTNN trên BCTC 2025 là 6.912,70 tỷ)
A27: TM 10.1-RL | B27: Tổng Nợ xấu Nhóm 3–5 (Riêng lẻ - Ngân hàng mẹ) | C27: tỷ | D27: 2598.623 | E27: 2327.978 | F27: 3625.232 | G27: 8121.854 | H27: 10493.355 | I27: 11517.998 | J27: TM 10.1 BCTC Riêng 2021-2024 & TM 9.1 2025 (Năm 2024 sau ĐC KTNN trên BCTC 2025 là 10.123,61 tỷ)
A28: TM 10.1-RL | B28: Tổng Dư nợ cho vay khách hàng Riêng lẻ | C28: tỷ | D28: =D25+D26+D27 | E28: =E25+E26+E27 | F28: =F25+F26+F27 | G28: =G25+G26+G27 | H28: =H25+H26+H27 | I28: =I25+I26+I27 | J28: Khớp 100% chỉ tiêu VI.1 trên Bảng cân đối kế toán Riêng lẻ
A29: Tỷ lệ | B29: Tỷ lệ NPL Riêng lẻ (= Nợ xấu Riêng / Dư nợ cho vay Riêng) | C29: % | D29: =D27/D28 | E29: =E27/E28 | F29: =F27/F28 | G29: =G27/G28 | H29: =H27/H28 | I29: =I27/I28 | J29: NPL riêng ngân hàng mẹ: 0,92% - 0,68% - 0,83% - 1,41% - 1,43% (ĐC: 1,38%) - 1,12%
A30: III | B30: BIẾN ĐỘNG DỰ PHÒNG RỦI RO CHO VAY KHÁCH HÀNG (TM 11 / 10)
A31: TM 11/10 | B31: Số dư Dự phòng chung cuối năm (Hợp nhất) | C31: tỷ | D31: 2148.238 | E31: 2590.776 | F31: 3400.915 | G31: 4551.746 | H31: 5795.573 | I31: 8098.145 | J31: TM 11 BCTC HN 2020 (tr.161), 2021 (tr.210), 2022 (tr.236), 2024 (tr.39), TM 10 2025 (tr.313)
A32: TM 11/10 | B32: Số dư Dự phòng cụ thể cuối năm (Hợp nhất) | C32: tỷ | D32: 2205.981 | E32: 6166.908 | F32: 8574.945 | G32: 6917.817 | H32: 5814.288 | I32: 5052.448 | J32: TM 11 BCTC HN 2020-2024 & TM 10 BCTC HN 2025
A33: TM 11/10 | B33: Tổng số dư Dự phòng rủi ro cho vay KH cuối năm (Hợp nhất) | C33: tỷ | D33: =D31+D32 | E33: =E31+E32 | F33: =F31+F32 | G33: =G31+G32 | H33: =H31+H32 | I33: =I31+I32 | J33: Tổng quỹ dự phòng rủi ro cho vay KH Hợp nhất = DP chung + DP cụ thể
A34: TM 11/10 | B34: Trích lập dự phòng rủi ro cho vay KH trong năm (Hợp nhất) | C34: tỷ | D34: 6139.086 | E34: 7953.801 | F34: 7873.697 | G34: 6114.903 | H34: 9534.768 | I34: 13690.356 | J34: TM 11 BCTC HN 2020-2024 & TM 10 BCTC HN 2025 (Trích lập DP chung + cụ thể)
A35: TM 11/10 | B35: Sử dụng dự phòng để xử lý rủi ro trong năm (Nợ xóa - Hợp nhất) | C35: tỷ | D35: 4980.2 | E35: 3542.937 | F35: 4412.07 | G35: 6622.439 | H35: 9396.915 | I35: 12185.137 | J35: TM 11 BCTC HN 2020 (tr.161), 2021 (tr.210), 2022 (tr.236), 2024 (tr.39), TM 10 2025 (tr.313)
A36: TM 11/10-RL | B36: Sử dụng dự phòng để xử lý rủi ro trong năm (Nợ xóa - Riêng lẻ) | C36: tỷ | D36: 3363.122 | E36: 2266.385 | F36: 2216.582 | G36: 4331.306 | H36: 5889.319 | I36: 7823.582 | J36: TM 11 BCTC Riêng 2021 (tr.33), 2022 (tr.35), 2024 (tr.39), TM 10 2025 (tr.34)
A37: Tỷ lệ | B37: Tỷ lệ bao phủ nợ xấu Hợp nhất (LLCR = Tổng DPRR HN / Nợ xấu HN) | C37: % | D37: =D33/D23 | E37: =E33/E23 | F37: =F33/F23 | G37: =G33/G23 | H37: =H33/H23 | I37: =I33/I23 | J37: LLCR Hợp nhất: 134,1% - 268,0% - 238,0% - 117,0% - 92,3% - 93,8%
A38: Tỷ lệ | B38: Tỷ lệ bao phủ nợ xấu Riêng lẻ (LLCR = Tổng DPRR Riêng / Nợ xấu Riêng) | C38: % | D38: =D11/D27 | E38: =E11/E27 | F38: =F11/F27 | G38: =G11/G27 | H38: =H11/H27 | I38: =I11/I27 | J38: LLCR Riêng lẻ: 158,9% - 348,7% - 295,3% - 115,5% - 94,5% (ĐC: 98,0%) - 101,0%
A39: IV | B39: BÁO CÁO KẾT QUẢ HOẠT ĐỘNG KINH DOANH HỢP NHẤT & THU NỢ XLRR
A40: B03-HN | B40: Thu nhập lãi thuần (NII - Hợp nhất) | C40: tỷ | D40: 20277.795 | E40: 26199.554 | F40: 36023.122 | G40: 38683.848 | H40: 41152.219 | I40: 51610.117 | J40: B03/TCTD-HN 2020-2025
A41: TM 31/32 | B41: Kết quả thuần từ hoạt động khác (Mục VI KQKD Hợp nhất) | C41: tỷ | D41: 1679.55 | E41: 3254.314 | F41: 2141.658 | G41: 2428.111 | H41: 3280.82 | I41: 5314.474 | J41: TM 31 BCTC HN 2020-2022, TM 32 BCTC HN 2024, TM 31 BCTC HN 2025
A42: TM 31/32 | B42: Trong đó: Thu từ các khoản nợ đã xử lý rủi ro (Hợp nhất) | C42: tỷ | D42: 1599.755 | E42: 2689.366 | F42: 1648.266 | G42: 1711.016 | H42: 2451.56 | I42: 4141.692 | J42: TM 31 BCTC HN 2020 (tr.173), 2021 (tr.222), 2022 (tr.249), TM 32 2024 (tr.55), TM 31 2025 (tr.327)
A43: B03-HN | B43: Tổng thu nhập hoạt động (TOI - Hợp nhất) | C43: tỷ | D43: 27362.173 | E43: 36934.498 | F43: 45592.625 | G43: 47306.062 | H43: 55413.222 | I43: 67693.015 | J43: B03/TCTD-HN 2020-2025
A44: TM 34/35 | B44: Tổng chi phí hoạt động (OPEX - Hợp nhất) | C44: tỷ | D44: 10555.457 | E44: 12377.188 | F44: 14815.628 | G44: 14912.941 | H44: 17007.25 | I44: 19681.153 | J44: B03/TCTD-HN 2020-2025
A45: B03-HN | B45: Lợi nhuận thuần từ HĐKD trước CP DPRR (PPOP - Hợp nhất) | C45: tỷ | D45: =D43-D44 | E45: =E43-E44 | F45: =F43-F44 | G45: =G43-G44 | H45: =H43-H44 | I45: =I43-I44 | J45: TOI trừ OPEX trên B03/TCTD-HN
A46: TM 35/36 | B46: Chi phí dự phòng rủi ro tín dụng trên KQKD (Hợp nhất) | C46: tỷ | D46: 6118.44 | E46: 8030.051 | F46: 8047.677 | G46: 6087.032 | H46: 9576.644 | I46: 13743.504 | J46: B03/TCTD-HN (Gồm trích lập DPRR cho vay KH + Mua nợ + Phải thu ký quỹ MBS + Cho vay TCTD)
A47: B03-HN | B47: Tổng lợi nhuận trước thuế (LNTT - Hợp nhất) | C47: tỷ | D47: =D45-D46 | E47: =E45-E46 | F47: =F45-F46 | G47: =G45-G46 | H47: =H45-H46 | I47: =I45-I46 | J47: B03/TCTD-HN 2020-2025
A48: B03-HN | B48: Lợi nhuận sau thuế (LNST - Hợp nhất) | C48: tỷ | D48: 8606.039 | E48: 13221.437 | F48: 18155.185 | G48: 21053.792 | H48: 22951.264 | I48: 27382.978 | J48: B03/TCTD-HN 2020-2025
A49: V | B49: TRÁI PHIẾU DOANH NGHIỆP, TÀI SẢN ĐẢM BẢO, DƯ NỢ NGÀNH & CÔNG TY CON
A50: TM 12.1 | B50: Chứng khoán nợ do TCKT phát hành - Sẵn sàng để bán (TPDN AFS) | C50: tỷ | D50: 24798.761 | E50: 39208.003 | F50: 43578.602 | G50: 35765.757 | H50: 31485.624 | I50: 21780.026 | J50: TM 12.1 BCTC HN 2020-2022, TM 13.1 2024 (tr.40), TM 12.1 2025 (tr.314)
A51: TM 12.2 | B51: Chứng khoán nợ do TCKT phát hành - Giữ đến đáo hạn (TPDN HTM) | C51: tỷ | D51: 2617.258 | E51: 3160.653 | F51: 3291.371 | G51: 2682.434 | H51: 1957.474 | I51: 1630.13 | J51: TM 12.2 BCTC HN 2020-2022, TM 13.2 2024 (tr.41), TM 12.2 2025 (tr.315)
A52: TM 12/13 | B52: Tổng Trái phiếu Doanh nghiệp (TCKT = AFS + HTM Gross) | C52: tỷ | D52: =D50+D51 | E52: =E50+E51 | F52: =F50+F51 | G52: =G50+G51 | H52: =H50+H51 | I52: =I50+I51 | J52: Giải quyết mâu thuẫn 2022: TPDN TCKT chuẩn = 46.870 tỷ (còn 66.307 tỷ là CK nợ TCTD)
A53: TM 12/13 | B53: Chứng khoán nợ do các TCTD trong nước phát hành (AFS + HTM) | C53: tỷ | D53: 19881.881 | E53: 47632.1 | F53: 68220.588 | G53: 50215.258 | H53: 105951.22 | I53: 138248.21 | J53: TM 12/13 BCTC HN (Riêng AFS năm 2022 là 66.307,37 tỷ HN / 66.279 tỷ Riêng lẻ)
A54: Tổng TD | B54: Tổng dư nợ tín dụng Hợp nhất (Cho vay KH + TPDN TCKT + Mua nợ) | C54: tỷ | D54: =D22+D52+D13 | E54: =E22+E52+E13 | F54: =F22+F52+F13 | G54: =G22+G52+G13 | H54: =H22+H52+H13 | I54: =I22+I52+I13 | J54: Khớp con số 'hơn 811 nghìn tỷ' năm 2024 (811.052 tỷ) trên BCTN 2024
A55: TM 39-42 | B55: Tổng giá trị Tài sản bảo đảm của khách hàng (Hợp nhất) | C55: tỷ | D55: 1018418.1 | E55: 1350936.2 | F55: 1379178.6 | G55: 1371243.5 | H55: 1481628.3 | I55: 2030363.3 | J55: TM 39.2 BCTC HN 2020, TM 40.2 2021-2022, TM 42.2 2024 (tr.69), TM 41.2 2025 (tr.341)
A56: TM 39-42 | B56: Trong đó: Bất động sản thế chấp của khách hàng | C56: tỷ | D56: 338549.57 | E56: 424065.45 | F56: 534896.91 | G56: 630518.71 | H56: 772485.56 | I56: 1025680.7 | J56: TM 39.2/40.2/42.2/41.2 BCTC HN (Chiếm 31,4% - 52,1% tổng TSĐB)
A57: TM 10.4 | B57: Dư nợ ngành Hoạt động kinh doanh bất động sản (Hợp nhất) | C57: tỷ | D57: 9395.157 | E57: 12632.155 | F57: 21357.811 | G57: 43268.446 | H57: 64141.215 | I57: 121188.71 | J57: TM 10.4 BCTC HN 2020-2024 & TM 9.4 2025 (Tăng từ 3,15% năm 2020 lên 11,18% năm 2025)
A58: TM 10.4 | B58: Dư nợ ngành Xây dựng (Hợp nhất) | C58: tỷ | D58: 18157.881 | E58: 22523.216 | F58: 26445.868 | G58: 28700.45 | H58: 31917.958 | I58: 45398.649 | J58: TM 10.4 BCTC HN 2020-2024 & TM 9.4 2025 (Chiếm 4,11% - 6,20% dư nợ)
A59: TM 10.4 | B59: Dư nợ cho vay tiêu dùng Khối Công ty con (MCredit & MBCambodia = HN - Riêng) | C59: tỷ | D59: 10173.263 | E59: 15117.992 | F59: 21624.031 | G59: 21388.364 | H59: 25434.734 | I59: 29622.319 | J59: Chênh lệch dòng 19 Hộ gia đình TM 10.4 HN và Riêng lẻ (MCredit là chủ yếu; MBV không hợp nhất theo Điều 185 Luật TCTD 2024, TM 3.4 tr.148)
A60: TM 10.1 | B60: Nợ xấu Nhóm 3–5 của Khối Công ty con (chủ yếu MCredit = Nợ xấu HN - Riêng) | C60: tỷ | D60: =D23-D27 | E60: =E23-E27 | F60: =F23-F27 | G60: =G23-G27 | H60: =H23-H27 | I60: =I23-I27 | J60: Bóc tách chính xác từ TM 10.1/9.1 BCTC Hợp nhất và Riêng lẻ (MBV không hợp nhất vào BCTC MB)
A61: TM 10.1 | B61: Dư nợ cho vay giao dịch ký quỹ & ứng trước của MBS (Nhóm 1) | C61: tỷ | D61: 4123.34 | E61: 7151.289 | F61: 3759.5 | G61: 9218.483 | H61: 10293.729 | I61: 15040.585 | J61: TM 10.1 BCTC HN 2020-2024 & TM 9.1 BCTC HN 2025
A62: BCTN | B62: Hệ số CAR Hợp nhất theo Thông tư 41 / Basel II | C62: % | D62: 0.1042 | E62: 0.1128 | F62: 0.1153 | G62: 0.1075 | H62: 0.118 | I62: 0.11 | J62: BCTN MB 2020 (tr.26), 2021 (tr.34), 2022 (tr.29), 2023 (tr.25), 2024 (tr.35), 2025 (tr.29)
A63: BCTN | B63: Dư nợ cơ cấu giữ nguyên nhóm nợ xác nhận từ BCTN (TT 01/03/14 & TT 02) | C63: tỷ | D63: 2850 | E63: 612 | F63: 0 | G63: 4100 | H63: 0 | I63: 0 | J63: BCTN 2021 (tr.41): dư nợ cơ cấu Covid cuối 2021 còn 612 tỷ (đã trích 100% DP); các năm 2020, 2023 không công bố số dư tuyệt đối trên BCTC
A64: B02-HN | B64: Dư nợ cho vay khách hàng gộp năm 2019 (TM 10 BCTC HN 2020 KPMG) | C64: tỷ | D64: 250330.62 | J64: TM 10 BCTC HN 2020 kiểm toán KPMG (BCTN 2020 tr.65/80 cột 31/12/2019: 250.330.623 triệu VND)
A65: TM 10.1 | B65: Nợ xấu nhóm 3–5 hợp nhất năm 2019 (TM 10.1 BCTC HN 2020 KPMG) | C65: tỷ | D65: 2897.638 | J65: TM 10.1 BCTC HN 2020 KPMG (tr.80: N3=1.380,4 tỷ; N4=899,3 tỷ; N5=617,9 tỷ; NPL=1,16%)
A66: TM 10.1 | B66: Nợ cần chú ý (Nhóm 2) năm 2019 (TM 10.1 BCTC HN 2020 KPMG) | C66: tỷ | D66: 2896.273 | J66: TM 10.1 BCTC HN 2020 kiểm toán KPMG (BCTN 2020 tr.80: Nợ nhóm 2 chiếm 1,16% tổng dư nợ cho vay)
A67: TM 11 | B67: Tổng số dư dự phòng rủi ro cho vay khách hàng năm 2019 (TM 11 BCTC 2020) | C67: tỷ | D67: 3200.913 | J67: Bảng CĐKT B02 và TM 11 BCTC HN 2020 kiểm toán KPMG (BCTN 2020 tr.65/80: LLCR 2019 = 110,5%)
A68: TM 32 | B68: Thu từ các khoản nợ đã xử lý rủi ro năm 2019 (TM 32 BCTC HN 2020 KPMG) | C68: tỷ | D68: 1937.102 | J68: TM 32 BCTC HN 2020 kiểm toán KPMG (BCTN 2020 tr.93, cột 2019: Thu từ nợ xấu đã được xử lý rủi ro)
A69: TM 10.4 | B69: Dư nợ cho vay kinh doanh Bất động sản năm 2019 (TM 10.4 BCTC HN 2020) | C69: tỷ | D69: 5356.894 | J69: TM 10.4 BCTC HN 2020 kiểm toán KPMG (BCTN 2020 tr.81: chiếm 2,14% tổng dư nợ cho vay)
A70: TM 10.4 | B70: Dư nợ cho vay ngành Xây dựng năm 2019 (TM 10.4 BCTC HN 2020) | C70: tỷ | D70: 19403.393 | J70: TM 10.4 BCTC HN 2020 kiểm toán KPMG (BCTN 2020 tr.81: chiếm 7,75% tổng dư nợ cho vay)
